[
  {
    "F_OUTAGE_ID": "112686",
    "OUTAGE_EXTENT": "CUSTOMER",
    "OUTAGE_DEVICE_ID": "599999555555",
    "OUTAGE_CIRCUIT_ID": 22011117,
    "CREW_ETA": null,
    "CREW_CURRENT_STATUS": "Awaiting T-Man",
    "OUTAGE_CAUSE": null,
    "EST_CUSTOMERS": 1,
    "OUTAGE_LATITUDE": 37.77854,
    "OUTAGE_LONGITUDE": -122.41421,
    "CITY": "San Francisco",
    "COUNTY": null,
    "ZIP": null,
    "DEVICE_COUNT": 0,
    "OUTAGE_START": 1766322089000,
    "OUTAGE_START_TEXT": "2025-12-21T13:01:29Z",
    "LAST_UPDATE": 1766322092000,
    "LAST_UPDATE_TEXT": "2025-12-21T13:01:32Z",
    "CURRENT_ETOR": 1766342700000,
    "CURRENT_ETOR_TEXT": "2025-12-21T18:45:00Z",
    "AUTO_ETOR": 1766342700000,
    "SPID": "9929546065",
    "fts_flag": "N",
    "geometry_x": -13627087.5231,
    "geometry_y": 4548188.0072999969
  },
  {
    "F_OUTAGE_ID": "112722",
    "OUTAGE_EXTENT": "SERVICE TRANSFORMER",
    "OUTAGE_DEVICE_ID": "411969753470",
    "OUTAGE_CIRCUIT_ID": 182352103,
    "CREW_ETA": null,
    "CREW_CURRENT_STATUS": "T-Man On Site",
    "OUTAGE_CAUSE": "PATROLLING",
    "EST_CUSTOMERS": 1,
    "OUTAGE_LATITUDE": 36.770569999999999,
    "OUTAGE_LONGITUDE": -121.74321,
    "CITY": "Prunedale",
    "COUNTY": null,
    "ZIP": null,
    "DEVICE_COUNT": 0,
    "OUTAGE_START": 1766324182000,
    "OUTAGE_START_TEXT": "2025-12-21T13:36:22Z",
    "LAST_UPDATE": 1766328482000,
    "LAST_UPDATE_TEXT": "2025-12-21T14:48:02Z",
    "CURRENT_ETOR": 1766338200000,
    "CURRENT_ETOR_TEXT": "2025-12-21T17:30:00Z",
    "AUTO_ETOR": 1766338200000,
    "SPID": null,
    "fts_flag": "N",
    "geometry_x": -13552392.1447,
    "geometry_y": 4407175.2705999985
  }
]
