[
  {
    "F_OUTAGE_ID": 2427913,
    "OUTAGE_EXTENT": "CUSTOMER",
    "OUTAGE_DEVICE_ID": "121491048213",
    "OUTAGE_CIRCUIT_ID": 103551101,
    "CREW_ETA": null,
    "CREW_CURRENT_STATUS": "Awaiting Crew",
    "OUTAGE_CAUSE": "PATROLLING",
    "EST_CUSTOMERS": 1,
    "OUTAGE_LATITUDE": 40.65543,
    "OUTAGE_LONGITUDE": -121.4637,
    "CITY": "Old Station",
    "COUNTY": null,
    "ZIP": null,
    "DEVICE_COUNT": 0,
    "OUTAGE_START": 1712753828000,
    "OUTAGE_START_TEXT": null,
    "LAST_UPDATE": 1712771274000,
    "LAST_UPDATE_TEXT": null,
    "CURRENT_ETOR": 1712862000000,
    "CURRENT_ETOR_TEXT": null,
    "AUTO_ETOR": null,
    "SPID": "730366905",
    "fts_flag": "N",
    "geometry_x": -13521277.2339,
    "geometry_y": 4961649.750500001
  },
  {
    "F_OUTAGE_ID": 2428111,
    "OUTAGE_EXTENT": "CUSTOMER",
    "OUTAGE_DEVICE_ID": "314388244786",
    "OUTAGE_CIRCUIT_ID": 22101105,
    "CREW_ETA": null,
    "CREW_CURRENT_STATUS": "Awaiting Crew",
    "OUTAGE_CAUSE": "REPLCE SRVC",
    "EST_CUSTOMERS": 1,
    "OUTAGE_LATITUDE": 37.71401,
    "OUTAGE_LONGITUDE": -122.4411,
    "CITY": "San Francisco",
    "COUNTY": null,
    "ZIP": null,
    "DEVICE_COUNT": 0,
    "OUTAGE_START": 1712775033000,
    "OUTAGE_START_TEXT": null,
    "LAST_UPDATE": 1712814692000,
    "LAST_UPDATE_TEXT": null,
    "CURRENT_ETOR": 1712822400000,
    "CURRENT_ETOR_TEXT": null,
    "AUTO_ETOR": null,
    "SPID": "5532649305",
    "fts_flag": "N",
    "geometry_x": -13630080.904199999,
    "geometry_y": 4539103.423100002
  },
  {
    "F_OUTAGE_ID": 2428143,
    "OUTAGE_EXTENT": "CUSTOMER",
    "OUTAGE_DEVICE_ID": "515670060160",
    "OUTAGE_CIRCUIT_ID": 252081101,
    "CREW_ETA": null,
    "CREW_CURRENT_STATUS": "Awaiting Crew",
    "OUTAGE_CAUSE": "PATROLLING",
    "EST_CUSTOMERS": 1,
    "OUTAGE_LATITUDE": 35.14432,
    "OUTAGE_LONGITUDE": -119.44941,
    "CITY": "Taft",
    "COUNTY": null,
    "ZIP": null,
    "DEVICE_COUNT": 0,
    "OUTAGE_START": 1712778001000,
    "OUTAGE_START_TEXT": null,
    "LAST_UPDATE": 1712796997000,
    "LAST_UPDATE_TEXT": null,
    "CURRENT_ETOR": 1712829600000,
    "CURRENT_ETOR_TEXT": null,
    "AUTO_ETOR": null,
    "SPID": "7902098605",
    "fts_flag": "N",
    "geometry_x": -13297047.4968,
    "geometry_y": 4183510.9922999963
  },
  {
    "F_OUTAGE_ID": 2428201,
    "OUTAGE_EXTENT": "CUSTOMER",
    "OUTAGE_DEVICE_ID": "217931926273",
    "OUTAGE_CIRCUIT_ID": 43181102,
    "CREW_ETA": null,
    "CREW_CURRENT_STATUS": "T-Man On Site",
    "OUTAGE_CAUSE": "PATROLLING",
    "EST_CUSTOMERS": 1,
    "OUTAGE_LATITUDE": 38.38572,
    "OUTAGE_LONGITUDE": -122.72276,
    "CITY": "Santa Rosa",
    "COUNTY": null,
    "ZIP": null,
    "DEVICE_COUNT": 0,
    "OUTAGE_START": 1712806589000,
    "OUTAGE_START_TEXT": null,
    "LAST_UPDATE": 1712814165000,
    "LAST_UPDATE_TEXT": null,
    "CURRENT_ETOR": 1712825100000,
    "CURRENT_ETOR_TEXT": null,
    "AUTO_ETOR": 1712825100000,
    "SPID": "9798458202",
    "fts_flag": "N",
    "geometry_x": -13661435.1519,
    "geometry_y": 4634059.329300001
  },
  {
    "F_OUTAGE_ID": 2428208,
    "OUTAGE_EXTENT": "CUSTOMER",
    "OUTAGE_DEVICE_ID": "314206140354",
    "OUTAGE_CIRCUIT_ID": 22811104,
    "CREW_ETA": null,
    "CREW_CURRENT_STATUS": "Awaiting T-Man",
    "OUTAGE_CAUSE": null,
    "EST_CUSTOMERS": 1,
    "OUTAGE_LATITUDE": 37.59161,
    "OUTAGE_LONGITUDE": -122.50111,
    "CITY": "Pacifica",
    "COUNTY": null,
    "ZIP": null,
    "DEVICE_COUNT": 0,
    "OUTAGE_START": 1712812026000,
    "OUTAGE_START_TEXT": null,
    "LAST_UPDATE": 1712812031000,
    "LAST_UPDATE_TEXT": null,
    "CURRENT_ETOR": 1712822400000,
    "CURRENT_ETOR_TEXT": null,
    "AUTO_ETOR": 1712822400000,
    "SPID": "5255416105",
    "fts_flag": "N",
    "geometry_x": -13636761.1868,
    "geometry_y": 4521893.560999997
  }
]
