[
  {
    "F_OUTAGE_ID": 2377822,
    "OUTAGE_EXTENT": "CUSTOMER",
    "OUTAGE_DEVICE_ID": "315544027949",
    "OUTAGE_CIRCUIT_ID": 83371107,
    "CREW_ETA": null,
    "CREW_CURRENT_STATUS": "Awaiting T-Man",
    "OUTAGE_CAUSE": null,
    "EST_CUSTOMERS": 1,
    "OUTAGE_LATITUDE": 37.25743,
    "OUTAGE_LONGITUDE": -122.03216,
    "CITY": "Saratoga",
    "COUNTY": null,
    "ZIP": null,
    "DEVICE_COUNT": 0,
    "OUTAGE_START": 1708070319000,
    "OUTAGE_START_TEXT": null,
    "LAST_UPDATE": 1708091923000,
    "LAST_UPDATE_TEXT": null,
    "CURRENT_ETOR": 1708106400000,
    "CURRENT_ETOR_TEXT": null,
    "AUTO_ETOR": 1708106400000,
    "SPID": "7895037305",
    "fts_flag": "N",
    "geometry_x": -13584557.911600001,
    "geometry_y": 4475050.2119999975
  },
  {
    "F_OUTAGE_ID": 2377886,
    "OUTAGE_EXTENT": "SERVICE TRANSFORMER",
    "OUTAGE_DEVICE_ID": "222661745194",
    "OUTAGE_CIRCUIT_ID": 152161102,
    "CREW_ETA": null,
    "CREW_CURRENT_STATUS": "Crew On Site",
    "OUTAGE_CAUSE": "PLNND SHUTDOWN",
    "EST_CUSTOMERS": 1,
    "OUTAGE_LATITUDE": 38.90384,
    "OUTAGE_LONGITUDE": -121.06584,
    "CITY": "Auburn",
    "COUNTY": null,
    "ZIP": null,
    "DEVICE_COUNT": 0,
    "OUTAGE_START": 1708072261000,
    "OUTAGE_START_TEXT": null,
    "LAST_UPDATE": 1708072428000,
    "LAST_UPDATE_TEXT": null,
    "CURRENT_ETOR": 1708092000000,
    "CURRENT_ETOR_TEXT": null,
    "AUTO_ETOR": null,
    "SPID": null,
    "fts_flag": "N",
    "geometry_x": -13476987.6613,
    "geometry_y": 4707906.822700001
  },
  {
    "F_OUTAGE_ID": 2378007,
    "OUTAGE_EXTENT": "CUSTOMER",
    "OUTAGE_DEVICE_ID": "315550527939",
    "OUTAGE_CIRCUIT_ID": 83371107,
    "CREW_ETA": null,
    "CREW_CURRENT_STATUS": "Awaiting T-Man",
    "OUTAGE_CAUSE": null,
    "EST_CUSTOMERS": 1,
    "OUTAGE_LATITUDE": 37.25711,
    "OUTAGE_LONGITUDE": -122.02997,
    "CITY": "Saratoga",
    "COUNTY": null,
    "ZIP": null,
    "DEVICE_COUNT": 0,
    "OUTAGE_START": 1708075380000,
    "OUTAGE_START_TEXT": null,
    "LAST_UPDATE": 1708096984000,
    "LAST_UPDATE_TEXT": null,
    "CURRENT_ETOR": 1708111800000,
    "CURRENT_ETOR_TEXT": null,
    "AUTO_ETOR": 1708111800000,
    "SPID": "8138575937",
    "fts_flag": "N",
    "geometry_x": -13584314.1219,
    "geometry_y": 4475005.456200004
  },
  {
    "F_OUTAGE_ID": 2378023,
    "OUTAGE_EXTENT": "CUSTOMER",
    "OUTAGE_DEVICE_ID": "417344653008",
    "OUTAGE_CIRCUIT_ID": 252701110,
    "CREW_ETA": null,
    "CREW_CURRENT_STATUS": "Awaiting T-Man",
    "OUTAGE_CAUSE": null,
    "EST_CUSTOMERS": 1,
    "OUTAGE_LATITUDE": 36.78648,
    "OUTAGE_LONGITUDE": -119.90825,
    "CITY": "Fresno",
    "COUNTY": null,
    "ZIP": null,
    "DEVICE_COUNT": 0,
    "OUTAGE_START": 1708075702000,
    "OUTAGE_START_TEXT": null,
    "LAST_UPDATE": 1708075702000,
    "LAST_UPDATE_TEXT": null,
    "CURRENT_ETOR": 1708100100000,
    "CURRENT_ETOR_TEXT": null,
    "AUTO_ETOR": 1708100100000,
    "SPID": "7277585805",
    "fts_flag": "N",
    "geometry_x": -13348125.3319,
    "geometry_y": 4409386.495099999
  },
  {
    "F_OUTAGE_ID": 2378079,
    "OUTAGE_EXTENT": "CUSTOMER",
    "OUTAGE_DEVICE_ID": "317913747211",
    "OUTAGE_CIRCUIT_ID": 162611703,
    "CREW_ETA": null,
    "CREW_CURRENT_STATUS": "Awaiting T-Man",
    "OUTAGE_CAUSE": "PATROLLING",
    "EST_CUSTOMERS": 1,
    "OUTAGE_LATITUDE": 37.79434,
    "OUTAGE_LONGITUDE": -121.22294,
    "CITY": "Manteca",
    "COUNTY": null,
    "ZIP": null,
    "DEVICE_COUNT": 0,
    "OUTAGE_START": 1708076091000,
    "OUTAGE_START_TEXT": null,
    "LAST_UPDATE": 1708096760000,
    "LAST_UPDATE_TEXT": null,
    "CURRENT_ETOR": 1708105500000,
    "CURRENT_ETOR_TEXT": null,
    "AUTO_ETOR": null,
    "SPID": "1923226151",
    "fts_flag": "N",
    "geometry_x": -13494475.9533,
    "geometry_y": 4550413.551899999
  },
  {
    "F_OUTAGE_ID": 2378085,
    "OUTAGE_EXTENT": "CUSTOMER",
    "OUTAGE_DEVICE_ID": "315482532356",
    "OUTAGE_CIRCUIT_ID": 82031108,
    "CREW_ETA": null,
    "CREW_CURRENT_STATUS": "Awaiting T-Man",
    "OUTAGE_CAUSE": null,
    "EST_CUSTOMERS": 1,
    "OUTAGE_LATITUDE": 37.37815,
    "OUTAGE_LONGITUDE": -122.05552,
    "CITY": "Sunnyvale",
    "COUNTY": null,
    "ZIP": null,
    "DEVICE_COUNT": 0,
    "OUTAGE_START": 1708078528000,
    "OUTAGE_START_TEXT": null,
    "LAST_UPDATE": 1708078678000,
    "LAST_UPDATE_TEXT": null,
    "CURRENT_ETOR": 1708115400000,
    "CURRENT_ETOR_TEXT": null,
    "AUTO_ETOR": 1708115400000,
    "SPID": "8947528510",
    "fts_flag": "N",
    "geometry_x": -13587158.3349,
    "geometry_y": 4491947.9147000015
  },
  {
    "F_OUTAGE_ID": 2378096,
    "OUTAGE_EXTENT": "CUSTOMER",
    "OUTAGE_DEVICE_ID": "314943336675",
    "OUTAGE_CIRCUIT_ID": 24180405,
    "CREW_ETA": null,
    "CREW_CURRENT_STATUS": "Crew On Site",
    "OUTAGE_CAUSE": "REPLCE SRVC",
    "EST_CUSTOMERS": 1,
    "OUTAGE_LATITUDE": 37.4943,
    "OUTAGE_LONGITUDE": -122.2441,
    "CITY": "Redwood City",
    "COUNTY": null,
    "ZIP": null,
    "DEVICE_COUNT": 0,
    "OUTAGE_START": 1708079520000,
    "OUTAGE_START_TEXT": null,
    "LAST_UPDATE": 1708087137000,
    "LAST_UPDATE_TEXT": null,
    "CURRENT_ETOR": 1708116300000,
    "CURRENT_ETOR_TEXT": null,
    "AUTO_ETOR": 1708116300000,
    "SPID": "6654986710",
    "fts_flag": "N",
    "geometry_x": -13608150.964499999,
    "geometry_y": 4508231.627300002
  },
  {
    "F_OUTAGE_ID": 2378107,
    "OUTAGE_EXTENT": "CUSTOMER",
    "OUTAGE_DEVICE_ID": "314782736803",
    "OUTAGE_CIRCUIT_ID": 24141102,
    "CREW_ETA": null,
    "CREW_CURRENT_STATUS": "T-Man On Site",
    "OUTAGE_CAUSE": "PATROLLING",
    "EST_CUSTOMERS": 1,
    "OUTAGE_LATITUDE": 37.49697,
    "OUTAGE_LONGITUDE": -122.2995,
    "CITY": "San Carlos",
    "COUNTY": null,
    "ZIP": null,
    "DEVICE_COUNT": 0,
    "OUTAGE_START": 1708080256000,
    "OUTAGE_START_TEXT": null,
    "LAST_UPDATE": 1708094666000,
    "LAST_UPDATE_TEXT": null,
    "CURRENT_ETOR": 1708100100000,
    "CURRENT_ETOR_TEXT": null,
    "AUTO_ETOR": null,
    "SPID": "3095645005",
    "fts_flag": "N",
    "geometry_x": -13614318.0643,
    "geometry_y": 4508606.246799998
  },
  {
    "F_OUTAGE_ID": 2378130,
    "OUTAGE_EXTENT": "CUSTOMER",
    "OUTAGE_DEVICE_ID": "315993729357",
    "OUTAGE_CIRCUIT_ID": 83701101,
    "CREW_ETA": null,
    "CREW_CURRENT_STATUS": "T-Man Enroute",
    "OUTAGE_CAUSE": null,
    "EST_CUSTOMERS": 1,
    "OUTAGE_LATITUDE": 37.29816,
    "OUTAGE_LONGITUDE": -121.8785,
    "CITY": "San Jose",
    "COUNTY": null,
    "ZIP": null,
    "DEVICE_COUNT": 0,
    "OUTAGE_START": 1708081181000,
    "OUTAGE_START_TEXT": null,
    "LAST_UPDATE": 1708081183000,
    "LAST_UPDATE_TEXT": null,
    "CURRENT_ETOR": 1708117200000,
    "CURRENT_ETOR_TEXT": null,
    "AUTO_ETOR": 1708117200000,
    "SPID": "8557983305",
    "fts_flag": "N",
    "geometry_x": -13567452.558600001,
    "geometry_y": 4480748.3342999965
  },
  {
    "F_OUTAGE_ID": 2378146,
    "OUTAGE_EXTENT": "CUSTOMER",
    "OUTAGE_DEVICE_ID": "219304515255",
    "OUTAGE_CIRCUIT_ID": 42041104,
    "CREW_ETA": null,
    "CREW_CURRENT_STATUS": "Awaiting Crew",
    "OUTAGE_CAUSE": "BRKN POLE",
    "EST_CUSTOMERS": 1,
    "OUTAGE_LATITUDE": 38.08537,
    "OUTAGE_LONGITUDE": -122.24269,
    "CITY": "Vallejo",
    "COUNTY": null,
    "ZIP": null,
    "DEVICE_COUNT": 0,
    "OUTAGE_START": 1708081826000,
    "OUTAGE_START_TEXT": null,
    "LAST_UPDATE": 1708091572000,
    "LAST_UPDATE_TEXT": null,
    "CURRENT_ETOR": 1708120800000,
    "CURRENT_ETOR_TEXT": null,
    "AUTO_ETOR": null,
    "SPID": "4315760710",
    "fts_flag": "N",
    "geometry_x": -13607994.004,
    "geometry_y": 4591492.7601
  },
  {
    "F_OUTAGE_ID": 2378155,
    "OUTAGE_EXTENT": "CUSTOMER",
    "OUTAGE_DEVICE_ID": "417602254696",
    "OUTAGE_CIRCUIT_ID": 254552105,
    "CREW_ETA": null,
    "CREW_CURRENT_STATUS": "Awaiting Crew",
    "OUTAGE_CAUSE": "DAMGE UG CABLE",
    "EST_CUSTOMERS": 1,
    "OUTAGE_LATITUDE": 36.83313,
    "OUTAGE_LONGITUDE": -119.82065,
    "CITY": "Fresno",
    "COUNTY": null,
    "ZIP": null,
    "DEVICE_COUNT": 0,
    "OUTAGE_START": 1708082280000,
    "OUTAGE_START_TEXT": null,
    "LAST_UPDATE": 1708097167000,
    "LAST_UPDATE_TEXT": null,
    "CURRENT_ETOR": 1708126200000,
    "CURRENT_ETOR_TEXT": null,
    "AUTO_ETOR": null,
    "SPID": "7453728110",
    "fts_flag": "N",
    "geometry_x": -13338373.7445,
    "geometry_y": 4415872.7146999985
  },
  {
    "F_OUTAGE_ID": 2378176,
    "OUTAGE_EXTENT": "CUSTOMER",
    "OUTAGE_DEVICE_ID": "100000077576",
    "OUTAGE_CIRCUIT_ID": 254552102,
    "CREW_ETA": null,
    "CREW_CURRENT_STATUS": "Awaiting T-Man",
    "OUTAGE_CAUSE": null,
    "EST_CUSTOMERS": 1,
    "OUTAGE_LATITUDE": 36.79559,
    "OUTAGE_LONGITUDE": -119.90101,
    "CITY": "Fresno",
    "COUNTY": null,
    "ZIP": null,
    "DEVICE_COUNT": 0,
    "OUTAGE_START": 1708083510000,
    "OUTAGE_START_TEXT": null,
    "LAST_UPDATE": 1708083512000,
    "LAST_UPDATE_TEXT": null,
    "CURRENT_ETOR": 1708111800000,
    "CURRENT_ETOR_TEXT": null,
    "AUTO_ETOR": 1708111800000,
    "SPID": "5972084595",
    "fts_flag": "N",
    "geometry_x": -13347319.378800001,
    "geometry_y": 4410652.8396999985
  },
  {
    "F_OUTAGE_ID": 2378177,
    "OUTAGE_EXTENT": "CUSTOMER",
    "OUTAGE_DEVICE_ID": "100000007673",
    "OUTAGE_CIRCUIT_ID": 163881101,
    "CREW_ETA": null,
    "CREW_CURRENT_STATUS": "Awaiting Crew",
    "OUTAGE_CAUSE": "EMERG REPAIRS",
    "EST_CUSTOMERS": 1,
    "OUTAGE_LATITUDE": 38.43585,
    "OUTAGE_LONGITUDE": -121.01288,
    "CITY": "Ione",
    "COUNTY": null,
    "ZIP": null,
    "DEVICE_COUNT": 0,
    "OUTAGE_START": 1708083516000,
    "OUTAGE_START_TEXT": null,
    "LAST_UPDATE": 1708095432000,
    "LAST_UPDATE_TEXT": null,
    "CURRENT_ETOR": 1708110000000,
    "CURRENT_ETOR_TEXT": null,
    "AUTO_ETOR": null,
    "SPID": "9186644405",
    "fts_flag": "N",
    "geometry_x": -13471092.181,
    "geometry_y": 4641181.092600003
  },
  {
    "F_OUTAGE_ID": 2378178,
    "OUTAGE_EXTENT": "CUSTOMER",
    "OUTAGE_DEVICE_ID": "315915628420",
    "OUTAGE_CIRCUIT_ID": 83431111,
    "CREW_ETA": null,
    "CREW_CURRENT_STATUS": "Awaiting T-Man",
    "OUTAGE_CAUSE": null,
    "EST_CUSTOMERS": 1,
    "OUTAGE_LATITUDE": 37.27214,
    "OUTAGE_LONGITUDE": -121.90489,
    "CITY": "San Jose",
    "COUNTY": null,
    "ZIP": null,
    "DEVICE_COUNT": 0,
    "OUTAGE_START": 1708083541000,
    "OUTAGE_START_TEXT": null,
    "LAST_UPDATE": 1708083545000,
    "LAST_UPDATE_TEXT": null,
    "CURRENT_ETOR": 1708103700000,
    "CURRENT_ETOR_TEXT": null,
    "AUTO_ETOR": 1708103700000,
    "SPID": "8464628805",
    "fts_flag": "N",
    "geometry_x": -13570390.280000001,
    "geometry_y": 4477107.783699997
  },
  {
    "F_OUTAGE_ID": 2378191,
    "OUTAGE_EXTENT": "CUSTOMER",
    "OUTAGE_DEVICE_ID": "217729952245",
    "OUTAGE_CIRCUIT_ID": 43351106,
    "CREW_ETA": null,
    "CREW_CURRENT_STATUS": "Awaiting T-Man",
    "OUTAGE_CAUSE": null,
    "EST_CUSTOMERS": 1,
    "OUTAGE_LATITUDE": 39.09843,
    "OUTAGE_LONGITUDE": -122.80114,
    "CITY": "Lucerne",
    "COUNTY": null,
    "ZIP": null,
    "DEVICE_COUNT": 0,
    "OUTAGE_START": 1708084432000,
    "OUTAGE_START_TEXT": null,
    "LAST_UPDATE": 1708084436000,
    "LAST_UPDATE_TEXT": null,
    "CURRENT_ETOR": 1708101900000,
    "CURRENT_ETOR_TEXT": null,
    "AUTO_ETOR": 1708101900000,
    "SPID": "3461165205",
    "fts_flag": "N",
    "geometry_x": -13670160.373599999,
    "geometry_y": 4735780.648699999
  },
  {
    "F_OUTAGE_ID": 2378204,
    "OUTAGE_EXTENT": "CUSTOMER",
    "OUTAGE_DEVICE_ID": "221358547194",
    "OUTAGE_CIRCUIT_ID": 153732106,
    "CREW_ETA": null,
    "CREW_CURRENT_STATUS": "T-Man On Site",
    "OUTAGE_CAUSE": "PATROLLING",
    "EST_CUSTOMERS": 1,
    "OUTAGE_LATITUDE": 38.96138,
    "OUTAGE_LONGITUDE": -121.52337,
    "CITY": "Rio Oso",
    "COUNTY": null,
    "ZIP": null,
    "DEVICE_COUNT": 0,
    "OUTAGE_START": 1708085370000,
    "OUTAGE_START_TEXT": null,
    "LAST_UPDATE": 1708094878000,
    "LAST_UPDATE_TEXT": null,
    "CURRENT_ETOR": 1708101000000,
    "CURRENT_ETOR_TEXT": null,
    "AUTO_ETOR": null,
    "SPID": "1318358805",
    "fts_flag": "N",
    "geometry_x": -13527919.6679,
    "geometry_y": 4716141.0978000015
  },
  {
    "F_OUTAGE_ID": 2378206,
    "OUTAGE_EXTENT": "CUSTOMER",
    "OUTAGE_DEVICE_ID": "314948555863",
    "OUTAGE_CIRCUIT_ID": 13921104,
    "CREW_ETA": null,
    "CREW_CURRENT_STATUS": "Awaiting Crew",
    "OUTAGE_CAUSE": "NG CONNECTION",
    "EST_CUSTOMERS": 1,
    "OUTAGE_LATITUDE": 38.02126,
    "OUTAGE_LONGITUDE": -122.25465,
    "CITY": "Rodeo",
    "COUNTY": null,
    "ZIP": null,
    "DEVICE_COUNT": 0,
    "OUTAGE_START": 1708085627000,
    "OUTAGE_START_TEXT": null,
    "LAST_UPDATE": 1708089032000,
    "LAST_UPDATE_TEXT": null,
    "CURRENT_ETOR": 1708109100000,
    "CURRENT_ETOR_TEXT": null,
    "AUTO_ETOR": 1708109100000,
    "SPID": "3174199905",
    "fts_flag": "N",
    "geometry_x": -13609325.3851,
    "geometry_y": 4582429.573299997
  },
  {
    "F_OUTAGE_ID": 2378207,
    "OUTAGE_EXTENT": "CUSTOMER",
    "OUTAGE_DEVICE_ID": "315707829425",
    "OUTAGE_CIRCUIT_ID": 83371111,
    "CREW_ETA": null,
    "CREW_CURRENT_STATUS": "Awaiting T-Man",
    "OUTAGE_CAUSE": null,
    "EST_CUSTOMERS": 1,
    "OUTAGE_LATITUDE": 37.29919,
    "OUTAGE_LONGITUDE": -121.97659,
    "CITY": "San Jose",
    "COUNTY": null,
    "ZIP": null,
    "DEVICE_COUNT": 0,
    "OUTAGE_START": 1708085640000,
    "OUTAGE_START_TEXT": null,
    "LAST_UPDATE": 1708085697000,
    "LAST_UPDATE_TEXT": null,
    "CURRENT_ETOR": 1708119000000,
    "CURRENT_ETOR_TEXT": null,
    "AUTO_ETOR": 1708119000000,
    "SPID": "8336194110",
    "fts_flag": "N",
    "geometry_x": -13578371.8875,
    "geometry_y": 4480892.471199997
  },
  {
    "F_OUTAGE_ID": 2378241,
    "OUTAGE_EXTENT": "CUSTOMER",
    "OUTAGE_DEVICE_ID": "317760862422",
    "OUTAGE_CIRCUIT_ID": 162111102,
    "CREW_ETA": null,
    "CREW_CURRENT_STATUS": "T-Man On Site",
    "OUTAGE_CAUSE": "PATROLLING",
    "EST_CUSTOMERS": 1,
    "OUTAGE_LATITUDE": 38.21181,
    "OUTAGE_LONGITUDE": -121.28026,
    "CITY": "Collierville",
    "COUNTY": null,
    "ZIP": null,
    "DEVICE_COUNT": 0,
    "OUTAGE_START": 1708088507000,
    "OUTAGE_START_TEXT": null,
    "LAST_UPDATE": 1708096883000,
    "LAST_UPDATE_TEXT": null,
    "CURRENT_ETOR": 1708119000000,
    "CURRENT_ETOR_TEXT": null,
    "AUTO_ETOR": 1708119000000,
    "SPID": "9754914005",
    "fts_flag": "N",
    "geometry_x": -13500856.7865,
    "geometry_y": 4609390.8244
  },
  {
    "F_OUTAGE_ID": 2378244,
    "OUTAGE_EXTENT": "CUSTOMER",
    "OUTAGE_DEVICE_ID": "599999846456",
    "OUTAGE_CIRCUIT_ID": 22090410,
    "CREW_ETA": null,
    "CREW_CURRENT_STATUS": "Awaiting T-Man",
    "OUTAGE_CAUSE": null,
    "EST_CUSTOMERS": 1,
    "OUTAGE_LATITUDE": 37.7867,
    "OUTAGE_LONGITUDE": -122.43661,
    "CITY": "San Francisco",
    "COUNTY": null,
    "ZIP": null,
    "DEVICE_COUNT": 0,
    "OUTAGE_START": 1708088520000,
    "OUTAGE_START_TEXT": null,
    "LAST_UPDATE": 1708096082000,
    "LAST_UPDATE_TEXT": null,
    "CURRENT_ETOR": 1708103700000,
    "CURRENT_ETOR_TEXT": null,
    "AUTO_ETOR": null,
    "SPID": "5851404010",
    "fts_flag": "N",
    "geometry_x": -13629581.0797,
    "geometry_y": 4549337.343099996
  },
  {
    "F_OUTAGE_ID": 2378249,
    "OUTAGE_EXTENT": "CUSTOMER",
    "OUTAGE_DEVICE_ID": "317619753897",
    "OUTAGE_CIRCUIT_ID": 163121101,
    "CREW_ETA": null,
    "CREW_CURRENT_STATUS": "Awaiting T-Man",
    "OUTAGE_CAUSE": null,
    "EST_CUSTOMERS": 1,
    "OUTAGE_LATITUDE": 37.97745,
    "OUTAGE_LONGITUDE": -121.32671,
    "CITY": "Stockton",
    "COUNTY": null,
    "ZIP": null,
    "DEVICE_COUNT": 0,
    "OUTAGE_START": 1708088748000,
    "OUTAGE_START_TEXT": null,
    "LAST_UPDATE": 1708088750000,
    "LAST_UPDATE_TEXT": null,
    "CURRENT_ETOR": 1708102800000,
    "CURRENT_ETOR_TEXT": null,
    "AUTO_ETOR": 1708102800000,
    "SPID": "9755222905",
    "fts_flag": "N",
    "geometry_x": -13506027.5768,
    "geometry_y": 4576240.743699998
  },
  {
    "F_OUTAGE_ID": 2378261,
    "OUTAGE_EXTENT": "CUSTOMER",
    "OUTAGE_DEVICE_ID": "315834144079",
    "OUTAGE_CIRCUIT_ID": 14232107,
    "CREW_ETA": null,
    "CREW_CURRENT_STATUS": "Awaiting Crew",
    "OUTAGE_CAUSE": "PATROLLING",
    "EST_CUSTOMERS": 1,
    "OUTAGE_LATITUDE": 37.70167,
    "OUTAGE_LONGITUDE": -121.94124,
    "CITY": "Dublin",
    "COUNTY": null,
    "ZIP": null,
    "DEVICE_COUNT": 0,
    "OUTAGE_START": 1708089330000,
    "OUTAGE_START_TEXT": null,
    "LAST_UPDATE": 1708094754000,
    "LAST_UPDATE_TEXT": null,
    "CURRENT_ETOR": 1708103700000,
    "CURRENT_ETOR_TEXT": null,
    "AUTO_ETOR": 1708103700000,
    "SPID": "2369123310",
    "fts_flag": "N",
    "geometry_x": -13574436.7435,
    "geometry_y": 4537367.0896999985
  },
  {
    "F_OUTAGE_ID": 2378264,
    "OUTAGE_EXTENT": "CUSTOMER",
    "OUTAGE_DEVICE_ID": "315707629459",
    "OUTAGE_CIRCUIT_ID": 83371111,
    "CREW_ETA": null,
    "CREW_CURRENT_STATUS": "Awaiting T-Man",
    "OUTAGE_CAUSE": null,
    "EST_CUSTOMERS": 1,
    "OUTAGE_LATITUDE": 37.29963,
    "OUTAGE_LONGITUDE": -121.97659,
    "CITY": "San Jose",
    "COUNTY": null,
    "ZIP": null,
    "DEVICE_COUNT": 0,
    "OUTAGE_START": 1708089519000,
    "OUTAGE_START_TEXT": null,
    "LAST_UPDATE": 1708089521000,
    "LAST_UPDATE_TEXT": null,
    "CURRENT_ETOR": 1708122600000,
    "CURRENT_ETOR_TEXT": null,
    "AUTO_ETOR": 1708122600000,
    "SPID": "8336199305",
    "fts_flag": "N",
    "geometry_x": -13578371.8875,
    "geometry_y": 4480954.044799998
  },
  {
    "F_OUTAGE_ID": 2378276,
    "OUTAGE_EXTENT": "CUSTOMER",
    "OUTAGE_DEVICE_ID": "222633937179",
    "OUTAGE_CIRCUIT_ID": 153612110,
    "CREW_ETA": null,
    "CREW_CURRENT_STATUS": "T-Man On Site",
    "OUTAGE_CAUSE": "PATROLLING",
    "EST_CUSTOMERS": 1,
    "OUTAGE_LATITUDE": 38.68391,
    "OUTAGE_LONGITUDE": -121.07842,
    "CITY": "El Dorado Hills",
    "COUNTY": null,
    "ZIP": null,
    "DEVICE_COUNT": 0,
    "OUTAGE_START": 1708090013000,
    "OUTAGE_START_TEXT": null,
    "LAST_UPDATE": 1708092661000,
    "LAST_UPDATE_TEXT": null,
    "CURRENT_ETOR": 1708109100000,
    "CURRENT_ETOR_TEXT": null,
    "AUTO_ETOR": 1708109100000,
    "SPID": "1579134305",
    "fts_flag": "N",
    "geometry_x": -13478388.0605,
    "geometry_y": 4676494.999899998
  },
  {
    "F_OUTAGE_ID": 2378277,
    "OUTAGE_EXTENT": "CUSTOMER",
    "OUTAGE_DEVICE_ID": "511391171795",
    "OUTAGE_CIRCUIT_ID": 182551102,
    "CREW_ETA": null,
    "CREW_CURRENT_STATUS": "T-Man Enroute",
    "OUTAGE_CAUSE": "PATROLLING",
    "EST_CUSTOMERS": 1,
    "OUTAGE_LATITUDE": 35.43878,
    "OUTAGE_LONGITUDE": -120.891,
    "CITY": "Cayucos",
    "COUNTY": null,
    "ZIP": null,
    "DEVICE_COUNT": 0,
    "OUTAGE_START": 1708090123000,
    "OUTAGE_START_TEXT": null,
    "LAST_UPDATE": 1708091344000,
    "LAST_UPDATE_TEXT": null,
    "CURRENT_ETOR": 1708104600000,
    "CURRENT_ETOR_TEXT": null,
    "AUTO_ETOR": 1708104600000,
    "SPID": "314883505",
    "fts_flag": "N",
    "geometry_x": -13457524.5615,
    "geometry_y": 4223670.626800001
  },
  {
    "F_OUTAGE_ID": 2378278,
    "OUTAGE_EXTENT": "CUSTOMER",
    "OUTAGE_DEVICE_ID": "314245643333",
    "OUTAGE_CIRCUIT_ID": 22641112,
    "CREW_ETA": null,
    "CREW_CURRENT_STATUS": "T-Man Enroute",
    "OUTAGE_CAUSE": "PATROLLING",
    "EST_CUSTOMERS": 1,
    "OUTAGE_LATITUDE": 37.67331,
    "OUTAGE_LONGITUDE": -122.48997,
    "CITY": "Daly City",
    "COUNTY": null,
    "ZIP": null,
    "DEVICE_COUNT": 0,
    "OUTAGE_START": 1708090140000,
    "OUTAGE_START_TEXT": null,
    "LAST_UPDATE": 1708095055000,
    "LAST_UPDATE_TEXT": null,
    "CURRENT_ETOR": 1708107300000,
    "CURRENT_ETOR_TEXT": null,
    "AUTO_ETOR": 1708107300000,
    "SPID": "5364238205",
    "fts_flag": "N",
    "geometry_x": -13635521.0877,
    "geometry_y": 4533377.7136999965
  },
  {
    "F_OUTAGE_ID": 2378283,
    "OUTAGE_EXTENT": "CUSTOMER",
    "OUTAGE_DEVICE_ID": "315701129785",
    "OUTAGE_CIRCUIT_ID": 83371114,
    "CREW_ETA": null,
    "CREW_CURRENT_STATUS": "T-Man On Site",
    "OUTAGE_CAUSE": "PATROLLING",
    "EST_CUSTOMERS": 1,
    "OUTAGE_LATITUDE": 37.30907,
    "OUTAGE_LONGITUDE": -121.9788,
    "CITY": "San Jose",
    "COUNTY": null,
    "ZIP": null,
    "DEVICE_COUNT": 0,
    "OUTAGE_START": 1708090403000,
    "OUTAGE_START_TEXT": null,
    "LAST_UPDATE": 1708096711000,
    "LAST_UPDATE_TEXT": null,
    "CURRENT_ETOR": 1708118100000,
    "CURRENT_ETOR_TEXT": null,
    "AUTO_ETOR": 1708118100000,
    "SPID": "8242291910",
    "fts_flag": "N",
    "geometry_x": -13578617.9036,
    "geometry_y": 4482275.165899999
  },
  {
    "F_OUTAGE_ID": 2378285,
    "OUTAGE_EXTENT": "CUSTOMER",
    "OUTAGE_DEVICE_ID": "314742454932",
    "OUTAGE_CIRCUIT_ID": 14261101,
    "CREW_ETA": "2/16/2024 5:05:00 PM",
    "CREW_CURRENT_STATUS": "T-Man On Site",
    "OUTAGE_CAUSE": "PATROLLING",
    "EST_CUSTOMERS": 1,
    "OUTAGE_LATITUDE": 37.99454,
    "OUTAGE_LONGITUDE": -122.32566,
    "CITY": "Tara Hills",
    "COUNTY": null,
    "ZIP": null,
    "DEVICE_COUNT": 0,
    "OUTAGE_START": 1708090492000,
    "OUTAGE_START_TEXT": null,
    "LAST_UPDATE": 1708096118000,
    "LAST_UPDATE_TEXT": null,
    "CURRENT_ETOR": 1708113600000,
    "CURRENT_ETOR_TEXT": null,
    "AUTO_ETOR": 1708113600000,
    "SPID": "3172931205",
    "fts_flag": "N",
    "geometry_x": -13617230.1822,
    "geometry_y": 4578654.5266999975
  },
  {
    "F_OUTAGE_ID": 2378290,
    "OUTAGE_EXTENT": "CUSTOMER",
    "OUTAGE_DEVICE_ID": "316706520190",
    "OUTAGE_CIRCUIT_ID": 83242105,
    "CREW_ETA": null,
    "CREW_CURRENT_STATUS": "Awaiting T-Man",
    "OUTAGE_CAUSE": null,
    "EST_CUSTOMERS": 1,
    "OUTAGE_LATITUDE": 37.04911,
    "OUTAGE_LONGITUDE": -121.62908,
    "CITY": "Gilroy",
    "COUNTY": null,
    "ZIP": null,
    "DEVICE_COUNT": 0,
    "OUTAGE_START": 1708090921000,
    "OUTAGE_START_TEXT": null,
    "LAST_UPDATE": 1708090922000,
    "LAST_UPDATE_TEXT": null,
    "CURRENT_ETOR": 1708122600000,
    "CURRENT_ETOR_TEXT": null,
    "AUTO_ETOR": 1708122600000,
    "SPID": "7705970205",
    "fts_flag": "N",
    "geometry_x": -13539687.2513,
    "geometry_y": 4445954.300399996
  },
  {
    "F_OUTAGE_ID": 2378297,
    "OUTAGE_EXTENT": "CUSTOMER",
    "OUTAGE_DEVICE_ID": "316102144547",
    "OUTAGE_CIRCUIT_ID": 14502110,
    "CREW_ETA": null,
    "CREW_CURRENT_STATUS": "T-Man Enroute",
    "OUTAGE_CAUSE": null,
    "EST_CUSTOMERS": 1,
    "OUTAGE_LATITUDE": 37.71542,
    "OUTAGE_LONGITUDE": -121.84887,
    "CITY": "Dublin",
    "COUNTY": null,
    "ZIP": null,
    "DEVICE_COUNT": 0,
    "OUTAGE_START": 1708091129000,
    "OUTAGE_START_TEXT": null,
    "LAST_UPDATE": 1708091134000,
    "LAST_UPDATE_TEXT": null,
    "CURRENT_ETOR": 1708121700000,
    "CURRENT_ETOR_TEXT": null,
    "AUTO_ETOR": 1708121700000,
    "SPID": "4822103025",
    "fts_flag": "N",
    "geometry_x": -13564154.1621,
    "geometry_y": 4539301.839400001
  },
  {
    "F_OUTAGE_ID": 2378298,
    "OUTAGE_EXTENT": "CUSTOMER",
    "OUTAGE_DEVICE_ID": "316065831297",
    "OUTAGE_CIRCUIT_ID": 82191106,
    "CREW_ETA": null,
    "CREW_CURRENT_STATUS": "Awaiting T-Man",
    "OUTAGE_CAUSE": null,
    "EST_CUSTOMERS": 1,
    "OUTAGE_LATITUDE": 37.35166,
    "OUTAGE_LONGITUDE": -121.85456,
    "CITY": "San Jose",
    "COUNTY": null,
    "ZIP": null,
    "DEVICE_COUNT": 0,
    "OUTAGE_START": 1708091486000,
    "OUTAGE_START_TEXT": null,
    "LAST_UPDATE": 1708091488000,
    "LAST_UPDATE_TEXT": null,
    "CURRENT_ETOR": 1708128000000,
    "CURRENT_ETOR_TEXT": null,
    "AUTO_ETOR": 1708128000000,
    "SPID": "8572146710",
    "fts_flag": "N",
    "geometry_x": -13564787.57,
    "geometry_y": 4488237.668799996
  },
  {
    "F_OUTAGE_ID": 2378299,
    "OUTAGE_EXTENT": "CUSTOMER",
    "OUTAGE_DEVICE_ID": "318986359546",
    "OUTAGE_CIRCUIT_ID": 162991103,
    "CREW_ETA": "2/16/2024 2:56:00 PM",
    "CREW_CURRENT_STATUS": "T-Man On Site",
    "OUTAGE_CAUSE": "PATROLLING",
    "EST_CUSTOMERS": 1,
    "OUTAGE_LATITUDE": 38.13499,
    "OUTAGE_LONGITUDE": -120.85341,
    "CITY": "Rancho Calaveras",
    "COUNTY": null,
    "ZIP": null,
    "DEVICE_COUNT": 0,
    "OUTAGE_START": 1708091498000,
    "OUTAGE_START_TEXT": null,
    "LAST_UPDATE": 1708095189000,
    "LAST_UPDATE_TEXT": null,
    "CURRENT_ETOR": 1708115400000,
    "CURRENT_ETOR_TEXT": null,
    "AUTO_ETOR": 1708115400000,
    "SPID": "3368788834",
    "fts_flag": "N",
    "geometry_x": -13453340.0618,
    "geometry_y": 4598512.962700002
  },
  {
    "F_OUTAGE_ID": 2378300,
    "OUTAGE_EXTENT": "CUSTOMER",
    "OUTAGE_DEVICE_ID": "320350752729",
    "OUTAGE_CIRCUIT_ID": 163351703,
    "CREW_ETA": null,
    "CREW_CURRENT_STATUS": "Crew Enroute",
    "OUTAGE_CAUSE": "DAMGE UG CABLE",
    "EST_CUSTOMERS": 1,
    "OUTAGE_LATITUDE": 37.94807,
    "OUTAGE_LONGITUDE": -120.37917,
    "CITY": "Sonora",
    "COUNTY": null,
    "ZIP": null,
    "DEVICE_COUNT": 0,
    "OUTAGE_START": 1708091520000,
    "OUTAGE_START_TEXT": null,
    "LAST_UPDATE": 1708096907000,
    "LAST_UPDATE_TEXT": null,
    "CURRENT_ETOR": 1708108200000,
    "CURRENT_ETOR_TEXT": null,
    "AUTO_ETOR": null,
    "SPID": "9671965705",
    "fts_flag": "N",
    "geometry_x": -13400547.9065,
    "geometry_y": 4572092.440700002
  },
  {
    "F_OUTAGE_ID": 2378301,
    "OUTAGE_EXTENT": "CUSTOMER",
    "OUTAGE_DEVICE_ID": "315553328065",
    "OUTAGE_CIRCUIT_ID": 83371107,
    "CREW_ETA": null,
    "CREW_CURRENT_STATUS": "Awaiting T-Man",
    "OUTAGE_CAUSE": null,
    "EST_CUSTOMERS": 1,
    "OUTAGE_LATITUDE": 37.26054,
    "OUTAGE_LONGITUDE": -122.02892,
    "CITY": "Saratoga",
    "COUNTY": null,
    "ZIP": null,
    "DEVICE_COUNT": 0,
    "OUTAGE_START": 1708091571000,
    "OUTAGE_START_TEXT": null,
    "LAST_UPDATE": 1708091573000,
    "LAST_UPDATE_TEXT": null,
    "CURRENT_ETOR": 1708128000000,
    "CURRENT_ETOR_TEXT": null,
    "AUTO_ETOR": 1708128000000,
    "SPID": "8138691705",
    "fts_flag": "N",
    "geometry_x": -13584197.236499999,
    "geometry_y": 4475485.1919
  },
  {
    "F_OUTAGE_ID": 2378302,
    "OUTAGE_EXTENT": "CUSTOMER",
    "OUTAGE_DEVICE_ID": "417450452264",
    "OUTAGE_CIRCUIT_ID": 253731112,
    "CREW_ETA": null,
    "CREW_CURRENT_STATUS": "Awaiting T-Man",
    "OUTAGE_CAUSE": null,
    "EST_CUSTOMERS": 1,
    "OUTAGE_LATITUDE": 36.76648,
    "OUTAGE_LONGITUDE": -119.87125,
    "CITY": "Fresno",
    "COUNTY": null,
    "ZIP": null,
    "DEVICE_COUNT": 0,
    "OUTAGE_START": 1708091622000,
    "OUTAGE_START_TEXT": null,
    "LAST_UPDATE": 1708091622000,
    "LAST_UPDATE_TEXT": null,
    "CURRENT_ETOR": 1708105500000,
    "CURRENT_ETOR_TEXT": null,
    "AUTO_ETOR": 1708105500000,
    "SPID": "7350938605",
    "fts_flag": "N",
    "geometry_x": -13344006.5108,
    "geometry_y": 4406606.903099999
  },
  {
    "F_OUTAGE_ID": 2378304,
    "OUTAGE_EXTENT": "CUSTOMER",
    "OUTAGE_DEVICE_ID": "315331742708",
    "OUTAGE_CIRCUIT_ID": 14381106,
    "CREW_ETA": null,
    "CREW_CURRENT_STATUS": "T-Man Enroute",
    "OUTAGE_CAUSE": null,
    "EST_CUSTOMERS": 1,
    "OUTAGE_LATITUDE": 37.66181,
    "OUTAGE_LONGITUDE": -122.11384,
    "CITY": "Hayward",
    "COUNTY": null,
    "ZIP": null,
    "DEVICE_COUNT": 0,
    "OUTAGE_START": 1708091674000,
    "OUTAGE_START_TEXT": null,
    "LAST_UPDATE": 1708091674000,
    "LAST_UPDATE_TEXT": null,
    "CURRENT_ETOR": 1708106400000,
    "CURRENT_ETOR_TEXT": null,
    "AUTO_ETOR": 1708106400000,
    "SPID": "2267952005",
    "fts_flag": "N",
    "geometry_x": -13593650.487599999,
    "geometry_y": 4531760.453400001
  },
  {
    "F_OUTAGE_ID": 2378307,
    "OUTAGE_EXTENT": "CUSTOMER",
    "OUTAGE_DEVICE_ID": "411471448050",
    "OUTAGE_CIRCUIT_ID": 182440421,
    "CREW_ETA": null,
    "CREW_CURRENT_STATUS": "T-Man On Site",
    "OUTAGE_CAUSE": "PATROLLING",
    "EST_CUSTOMERS": 1,
    "OUTAGE_LATITUDE": 36.61749,
    "OUTAGE_LONGITUDE": -121.90828,
    "CITY": "Pacific Grove",
    "COUNTY": null,
    "ZIP": null,
    "DEVICE_COUNT": 0,
    "OUTAGE_START": 1708091832000,
    "OUTAGE_START_TEXT": null,
    "LAST_UPDATE": 1708095812000,
    "LAST_UPDATE_TEXT": null,
    "CURRENT_ETOR": 1708118100000,
    "CURRENT_ETOR_TEXT": null,
    "AUTO_ETOR": 1708118100000,
    "SPID": "44067905",
    "fts_flag": "N",
    "geometry_x": -13570767.653099999,
    "geometry_y": 4385923.097199999
  },
  {
    "F_OUTAGE_ID": 2378312,
    "OUTAGE_EXTENT": "CUSTOMER",
    "OUTAGE_DEVICE_ID": "316110230391",
    "OUTAGE_CIRCUIT_ID": 83392106,
    "CREW_ETA": null,
    "CREW_CURRENT_STATUS": "Awaiting T-Man",
    "OUTAGE_CAUSE": null,
    "EST_CUSTOMERS": 1,
    "OUTAGE_LATITUDE": 37.327,
    "OUTAGE_LONGITUDE": -121.83875,
    "CITY": "San Jose",
    "COUNTY": null,
    "ZIP": null,
    "DEVICE_COUNT": 0,
    "OUTAGE_START": 1708092027000,
    "OUTAGE_START_TEXT": null,
    "LAST_UPDATE": 1708092029000,
    "LAST_UPDATE_TEXT": null,
    "CURRENT_ETOR": 1708105500000,
    "CURRENT_ETOR_TEXT": null,
    "AUTO_ETOR": 1708105500000,
    "SPID": "8644789905",
    "fts_flag": "N",
    "geometry_x": -13563027.6089,
    "geometry_y": 4484784.913099997
  },
  {
    "F_OUTAGE_ID": 2378314,
    "OUTAGE_EXTENT": "CUSTOMER",
    "OUTAGE_DEVICE_ID": "315884927870",
    "OUTAGE_CIRCUIT_ID": 83431113,
    "CREW_ETA": null,
    "CREW_CURRENT_STATUS": "Awaiting T-Man",
    "OUTAGE_CAUSE": null,
    "EST_CUSTOMERS": 1,
    "OUTAGE_LATITUDE": 37.25691,
    "OUTAGE_LONGITUDE": -121.91508,
    "CITY": "San Jose",
    "COUNTY": null,
    "ZIP": null,
    "DEVICE_COUNT": 0,
    "OUTAGE_START": 1708092092000,
    "OUTAGE_START_TEXT": null,
    "LAST_UPDATE": 1708092093000,
    "LAST_UPDATE_TEXT": null,
    "CURRENT_ETOR": 1708128900000,
    "CURRENT_ETOR_TEXT": null,
    "AUTO_ETOR": 1708128900000,
    "SPID": "8413018105",
    "fts_flag": "N",
    "geometry_x": -13571524.625599999,
    "geometry_y": 4474977.483999997
  },
  {
    "F_OUTAGE_ID": 2378317,
    "OUTAGE_EXTENT": "CUSTOMER",
    "OUTAGE_DEVICE_ID": "221081053201",
    "OUTAGE_CIRCUIT_ID": 153781102,
    "CREW_ETA": null,
    "CREW_CURRENT_STATUS": "T-Man On Site",
    "OUTAGE_CAUSE": "PATROLLING",
    "EST_CUSTOMERS": 1,
    "OUTAGE_LATITUDE": 39.12663,
    "OUTAGE_LONGITUDE": -121.62015,
    "CITY": "Yuba City",
    "COUNTY": null,
    "ZIP": null,
    "DEVICE_COUNT": 0,
    "OUTAGE_START": 1708092144000,
    "OUTAGE_START_TEXT": null,
    "LAST_UPDATE": 1708093851000,
    "LAST_UPDATE_TEXT": null,
    "CURRENT_ETOR": 1708113600000,
    "CURRENT_ETOR_TEXT": null,
    "AUTO_ETOR": 1708113600000,
    "SPID": "1169802405",
    "fts_flag": "N",
    "geometry_x": -13538693.168200001,
    "geometry_y": 4739826.499200001
  },
  {
    "F_OUTAGE_ID": 2378319,
    "OUTAGE_EXTENT": "CUSTOMER",
    "OUTAGE_DEVICE_ID": "315888428334",
    "OUTAGE_CIRCUIT_ID": 83431111,
    "CREW_ETA": null,
    "CREW_CURRENT_STATUS": "Awaiting T-Man",
    "OUTAGE_CAUSE": null,
    "EST_CUSTOMERS": 1,
    "OUTAGE_LATITUDE": 37.2697,
    "OUTAGE_LONGITUDE": -121.91416,
    "CITY": "San Jose",
    "COUNTY": null,
    "ZIP": null,
    "DEVICE_COUNT": 0,
    "OUTAGE_START": 1708092241000,
    "OUTAGE_START_TEXT": null,
    "LAST_UPDATE": 1708092244000,
    "LAST_UPDATE_TEXT": null,
    "CURRENT_ETOR": 1708111800000,
    "CURRENT_ETOR_TEXT": null,
    "AUTO_ETOR": 1708111800000,
    "SPID": "8225016305",
    "fts_flag": "N",
    "geometry_x": -13571422.2117,
    "geometry_y": 4476766.459100001
  },
  {
    "F_OUTAGE_ID": 2378321,
    "OUTAGE_EXTENT": "CUSTOMER",
    "OUTAGE_DEVICE_ID": "512726354349",
    "OUTAGE_CIRCUIT_ID": 182671106,
    "CREW_ETA": null,
    "CREW_CURRENT_STATUS": "T-Man On Site",
    "OUTAGE_CAUSE": "PATROLLING",
    "EST_CUSTOMERS": 1,
    "OUTAGE_LATITUDE": 34.9693,
    "OUTAGE_LONGITUDE": -120.42903,
    "CITY": "Santa Maria",
    "COUNTY": null,
    "ZIP": null,
    "DEVICE_COUNT": 0,
    "OUTAGE_START": 1708092329000,
    "OUTAGE_START_TEXT": null,
    "LAST_UPDATE": 1708095647000,
    "LAST_UPDATE_TEXT": null,
    "CURRENT_ETOR": 1708115400000,
    "CURRENT_ETOR_TEXT": null,
    "AUTO_ETOR": 1708115400000,
    "SPID": "509184005",
    "fts_flag": "N",
    "geometry_x": -13406098.2963,
    "geometry_y": 4159709.918899998
  },
  {
    "F_OUTAGE_ID": 2378323,
    "OUTAGE_EXTENT": "CUSTOMER",
    "OUTAGE_DEVICE_ID": "219920521898",
    "OUTAGE_CIRCUIT_ID": 62131104,
    "CREW_ETA": null,
    "CREW_CURRENT_STATUS": "T-Man On Site",
    "OUTAGE_CAUSE": "PATROLLING",
    "EST_CUSTOMERS": 1,
    "OUTAGE_LATITUDE": 38.26785,
    "OUTAGE_LONGITUDE": -122.02876,
    "CITY": "Fairfield",
    "COUNTY": null,
    "ZIP": null,
    "DEVICE_COUNT": 0,
    "OUTAGE_START": 1708092463000,
    "OUTAGE_START_TEXT": null,
    "LAST_UPDATE": 1708094175000,
    "LAST_UPDATE_TEXT": null,
    "CURRENT_ETOR": 1708105500000,
    "CURRENT_ETOR_TEXT": null,
    "AUTO_ETOR": 1708105500000,
    "SPID": "4303476510",
    "fts_flag": "N",
    "geometry_x": -13584179.4253,
    "geometry_y": 4617333.442000002
  },
  {
    "F_OUTAGE_ID": 2378324,
    "OUTAGE_EXTENT": "CUSTOMER",
    "OUTAGE_DEVICE_ID": "314944650953",
    "OUTAGE_CIRCUIT_ID": 12501105,
    "CREW_ETA": null,
    "CREW_CURRENT_STATUS": "T-Man On Site",
    "OUTAGE_CAUSE": "PATROLLING",
    "EST_CUSTOMERS": 1,
    "OUTAGE_LATITUDE": 37.88637,
    "OUTAGE_LONGITUDE": -122.25293,
    "CITY": "Berkeley",
    "COUNTY": null,
    "ZIP": null,
    "DEVICE_COUNT": 0,
    "OUTAGE_START": 1708092594000,
    "OUTAGE_START_TEXT": null,
    "LAST_UPDATE": 1708095542000,
    "LAST_UPDATE_TEXT": null,
    "CURRENT_ETOR": 1708102800000,
    "CURRENT_ETOR_TEXT": null,
    "AUTO_ETOR": 1708102800000,
    "SPID": "3190685605",
    "fts_flag": "N",
    "geometry_x": -13609133.9156,
    "geometry_y": 4563386.117600001
  },
  {
    "F_OUTAGE_ID": 2378326,
    "OUTAGE_EXTENT": "CUSTOMER",
    "OUTAGE_DEVICE_ID": "315930329267",
    "OUTAGE_CIRCUIT_ID": 83701101,
    "CREW_ETA": null,
    "CREW_CURRENT_STATUS": "Awaiting T-Man",
    "OUTAGE_CAUSE": null,
    "EST_CUSTOMERS": 1,
    "OUTAGE_LATITUDE": 37.29543,
    "OUTAGE_LONGITUDE": -121.90025,
    "CITY": "San Jose",
    "COUNTY": null,
    "ZIP": null,
    "DEVICE_COUNT": 0,
    "OUTAGE_START": 1708092612000,
    "OUTAGE_START_TEXT": null,
    "LAST_UPDATE": 1708092614000,
    "LAST_UPDATE_TEXT": null,
    "CURRENT_ETOR": 1708128900000,
    "CURRENT_ETOR_TEXT": null,
    "AUTO_ETOR": 1708128900000,
    "SPID": "8410805205",
    "fts_flag": "N",
    "geometry_x": -13569873.7576,
    "geometry_y": 4480366.3112
  },
  {
    "F_OUTAGE_ID": 2378327,
    "OUTAGE_EXTENT": "CUSTOMER",
    "OUTAGE_DEVICE_ID": "217914028046",
    "OUTAGE_CIRCUIT_ID": 42151105,
    "CREW_ETA": null,
    "CREW_CURRENT_STATUS": "T-Man Enroute",
    "OUTAGE_CAUSE": null,
    "EST_CUSTOMERS": 1,
    "OUTAGE_LATITUDE": 38.43426,
    "OUTAGE_LONGITUDE": -122.72923,
    "CITY": "Santa Rosa",
    "COUNTY": null,
    "ZIP": null,
    "DEVICE_COUNT": 0,
    "OUTAGE_START": 1708092637000,
    "OUTAGE_START_TEXT": null,
    "LAST_UPDATE": 1708092970000,
    "LAST_UPDATE_TEXT": null,
    "CURRENT_ETOR": 1708128900000,
    "CURRENT_ETOR_TEXT": null,
    "AUTO_ETOR": 1708128900000,
    "SPID": "3952335505",
    "fts_flag": "N",
    "geometry_x": -13662155.3891,
    "geometry_y": 4640955.131899998
  },
  {
    "F_OUTAGE_ID": 2378328,
    "OUTAGE_EXTENT": "CUSTOMER",
    "OUTAGE_DEVICE_ID": "223868239579",
    "OUTAGE_CIRCUIT_ID": 153661104,
    "CREW_ETA": null,
    "CREW_CURRENT_STATUS": "T-Man On Site",
    "OUTAGE_CAUSE": "PATROLLING",
    "EST_CUSTOMERS": 1,
    "OUTAGE_LATITUDE": 38.74532,
    "OUTAGE_LONGITUDE": -120.64477,
    "CITY": "Camino",
    "COUNTY": null,
    "ZIP": null,
    "DEVICE_COUNT": 0,
    "OUTAGE_START": 1708092723000,
    "OUTAGE_START_TEXT": null,
    "LAST_UPDATE": 1708096735000,
    "LAST_UPDATE_TEXT": null,
    "CURRENT_ETOR": 1708110900000,
    "CURRENT_ETOR_TEXT": null,
    "AUTO_ETOR": 1708110900000,
    "SPID": "1436346505",
    "fts_flag": "N",
    "geometry_x": -13430114.3633,
    "geometry_y": 4685256.2272000015
  },
  {
    "F_OUTAGE_ID": 2378330,
    "OUTAGE_EXTENT": "CUSTOMER",
    "OUTAGE_DEVICE_ID": "512569144502",
    "OUTAGE_CIRCUIT_ID": 183101104,
    "CREW_ETA": null,
    "CREW_CURRENT_STATUS": "T-Man On Site",
    "OUTAGE_CAUSE": "PATROLLING",
    "EST_CUSTOMERS": 1,
    "OUTAGE_LATITUDE": 34.69719,
    "OUTAGE_LONGITUDE": -120.47272,
    "CITY": "Vandenberg Village",
    "COUNTY": null,
    "ZIP": null,
    "DEVICE_COUNT": 0,
    "OUTAGE_START": 1708092987000,
    "OUTAGE_START_TEXT": null,
    "LAST_UPDATE": 1708096206000,
    "LAST_UPDATE_TEXT": null,
    "CURRENT_ETOR": 1708109100000,
    "CURRENT_ETOR_TEXT": null,
    "AUTO_ETOR": 1708109100000,
    "SPID": "568710405",
    "fts_flag": "N",
    "geometry_x": -13410961.8449,
    "geometry_y": 4122806.2380999997
  },
  {
    "F_OUTAGE_ID": 2378332,
    "OUTAGE_EXTENT": "CUSTOMER",
    "OUTAGE_DEVICE_ID": "217835430487",
    "OUTAGE_CIRCUIT_ID": 42561102,
    "CREW_ETA": null,
    "CREW_CURRENT_STATUS": "Awaiting T-Man",
    "OUTAGE_CAUSE": null,
    "EST_CUSTOMERS": 1,
    "OUTAGE_LATITUDE": 38.50114,
    "OUTAGE_LONGITUDE": -122.75764,
    "CITY": "Larkfield-Wikiup",
    "COUNTY": null,
    "ZIP": null,
    "DEVICE_COUNT": 0,
    "OUTAGE_START": 1708093094000,
    "OUTAGE_START_TEXT": null,
    "LAST_UPDATE": 1708093103000,
    "LAST_UPDATE_TEXT": null,
    "CURRENT_ETOR": 1708104600000,
    "CURRENT_ETOR_TEXT": null,
    "AUTO_ETOR": 1708104600000,
    "SPID": "3743712110",
    "fts_flag": "N",
    "geometry_x": -13665317.9758,
    "geometry_y": 4650463.993500002
  },
  {
    "F_OUTAGE_ID": 2378334,
    "OUTAGE_EXTENT": "CUSTOMER",
    "OUTAGE_DEVICE_ID": "315308455566",
    "OUTAGE_CIRCUIT_ID": 13432207,
    "CREW_ETA": null,
    "CREW_CURRENT_STATUS": "Awaiting T-Man",
    "OUTAGE_CAUSE": null,
    "EST_CUSTOMERS": 1,
    "OUTAGE_LATITUDE": 38.01474,
    "OUTAGE_LONGITUDE": -122.12962,
    "CITY": "Martinez",
    "COUNTY": null,
    "ZIP": null,
    "DEVICE_COUNT": 0,
    "OUTAGE_START": 1708093156000,
    "OUTAGE_START_TEXT": null,
    "LAST_UPDATE": 1708093161000,
    "LAST_UPDATE_TEXT": null,
    "CURRENT_ETOR": 1708104600000,
    "CURRENT_ETOR_TEXT": null,
    "AUTO_ETOR": 1708104600000,
    "SPID": "1574395505",
    "fts_flag": "N",
    "geometry_x": -13595407.1092,
    "geometry_y": 4581508.289800003
  },
  {
    "F_OUTAGE_ID": 2378345,
    "OUTAGE_EXTENT": "CUSTOMER",
    "OUTAGE_DEVICE_ID": "516141165888",
    "OUTAGE_CIRCUIT_ID": 254691101,
    "CREW_ETA": null,
    "CREW_CURRENT_STATUS": "Awaiting T-Man",
    "OUTAGE_CAUSE": null,
    "EST_CUSTOMERS": 1,
    "OUTAGE_LATITUDE": 35.30437,
    "OUTAGE_LONGITUDE": -119.29406,
    "CITY": "Tupman",
    "COUNTY": null,
    "ZIP": null,
    "DEVICE_COUNT": 0,
    "OUTAGE_START": 1708093459000,
    "OUTAGE_START_TEXT": null,
    "LAST_UPDATE": 1708093560000,
    "LAST_UPDATE_TEXT": null,
    "CURRENT_ETOR": 1708110900000,
    "CURRENT_ETOR_TEXT": null,
    "AUTO_ETOR": 1708110900000,
    "SPID": "7260741907",
    "fts_flag": "N",
    "geometry_x": -13279754.0139,
    "geometry_y": 4205321.126100004
  },
  {
    "F_OUTAGE_ID": 2378347,
    "OUTAGE_EXTENT": "CUSTOMER",
    "OUTAGE_DEVICE_ID": "221360333864",
    "OUTAGE_CIRCUIT_ID": 63131109,
    "CREW_ETA": null,
    "CREW_CURRENT_STATUS": "T-Man On Site",
    "OUTAGE_CAUSE": "PATROLLING",
    "EST_CUSTOMERS": 1,
    "OUTAGE_LATITUDE": 38.59545,
    "OUTAGE_LONGITUDE": -121.52516,
    "CITY": "West Sacramento",
    "COUNTY": null,
    "ZIP": null,
    "DEVICE_COUNT": 0,
    "OUTAGE_START": 1708093604000,
    "OUTAGE_START_TEXT": null,
    "LAST_UPDATE": 1708095758000,
    "LAST_UPDATE_TEXT": null,
    "CURRENT_ETOR": 1708113600000,
    "CURRENT_ETOR_TEXT": null,
    "AUTO_ETOR": 1708113600000,
    "SPID": "5025850910",
    "fts_flag": "N",
    "geometry_x": -13528118.9298,
    "geometry_y": 4663887.814000003
  },
  {
    "F_OUTAGE_ID": 2378351,
    "OUTAGE_EXTENT": "CUSTOMER",
    "OUTAGE_DEVICE_ID": "314721438869",
    "OUTAGE_CIRCUIT_ID": 24040404,
    "CREW_ETA": null,
    "CREW_CURRENT_STATUS": "Awaiting T-Man",
    "OUTAGE_CAUSE": null,
    "EST_CUSTOMERS": 1,
    "OUTAGE_LATITUDE": 37.55338,
    "OUTAGE_LONGITUDE": -122.32207,
    "CITY": "San Mateo",
    "COUNTY": null,
    "ZIP": null,
    "DEVICE_COUNT": 0,
    "OUTAGE_START": 1708094034000,
    "OUTAGE_START_TEXT": null,
    "LAST_UPDATE": 1708094036000,
    "LAST_UPDATE_TEXT": null,
    "CURRENT_ETOR": 1708129800000,
    "CURRENT_ETOR_TEXT": null,
    "AUTO_ETOR": 1708129800000,
    "SPID": "6305390810",
    "fts_flag": "N",
    "geometry_x": -13616830.5452,
    "geometry_y": 4516524.095299996
  },
  {
    "F_OUTAGE_ID": 2378355,
    "OUTAGE_EXTENT": "CUSTOMER",
    "OUTAGE_DEVICE_ID": "314414045512",
    "OUTAGE_CIRCUIT_ID": 22270403,
    "CREW_ETA": null,
    "CREW_CURRENT_STATUS": "Awaiting T-Man",
    "OUTAGE_CAUSE": null,
    "EST_CUSTOMERS": 1,
    "OUTAGE_LATITUDE": 37.73406,
    "OUTAGE_LONGITUDE": -122.43274,
    "CITY": "San Francisco",
    "COUNTY": null,
    "ZIP": null,
    "DEVICE_COUNT": 0,
    "OUTAGE_START": 1708094251000,
    "OUTAGE_START_TEXT": null,
    "LAST_UPDATE": 1708094253000,
    "LAST_UPDATE_TEXT": null,
    "CURRENT_ETOR": 1708119000000,
    "CURRENT_ETOR_TEXT": null,
    "AUTO_ETOR": 1708119000000,
    "SPID": "6584410205",
    "fts_flag": "N",
    "geometry_x": -13629150.2732,
    "geometry_y": 4541925.229800001
  },
  {
    "F_OUTAGE_ID": 2378357,
    "OUTAGE_EXTENT": "CUSTOMER",
    "OUTAGE_DEVICE_ID": "317457743938",
    "OUTAGE_CIRCUIT_ID": 169951104,
    "CREW_ETA": null,
    "CREW_CURRENT_STATUS": "Awaiting T-Man",
    "OUTAGE_CAUSE": null,
    "EST_CUSTOMERS": 1,
    "OUTAGE_LATITUDE": 37.70345,
    "OUTAGE_LONGITUDE": -121.37978,
    "CITY": "Tracy",
    "COUNTY": null,
    "ZIP": null,
    "DEVICE_COUNT": 0,
    "OUTAGE_START": 1708094372000,
    "OUTAGE_START_TEXT": null,
    "LAST_UPDATE": 1708094482000,
    "LAST_UPDATE_TEXT": null,
    "CURRENT_ETOR": 1708105500000,
    "CURRENT_ETOR_TEXT": null,
    "AUTO_ETOR": 1708105500000,
    "SPID": "9938255210",
    "fts_flag": "N",
    "geometry_x": -13511935.3022,
    "geometry_y": 4537617.5317
  },
  {
    "F_OUTAGE_ID": 2378359,
    "OUTAGE_EXTENT": "CUSTOMER",
    "OUTAGE_DEVICE_ID": "315230544222",
    "OUTAGE_CIRCUIT_ID": 13111108,
    "CREW_ETA": null,
    "CREW_CURRENT_STATUS": "T-Man Enroute",
    "OUTAGE_CAUSE": null,
    "EST_CUSTOMERS": 1,
    "OUTAGE_LATITUDE": 37.70296,
    "OUTAGE_LONGITUDE": -122.14968,
    "CITY": "San Leandro",
    "COUNTY": null,
    "ZIP": null,
    "DEVICE_COUNT": 0,
    "OUTAGE_START": 1708094424000,
    "OUTAGE_START_TEXT": null,
    "LAST_UPDATE": 1708094427000,
    "LAST_UPDATE_TEXT": null,
    "CURRENT_ETOR": 1708111800000,
    "CURRENT_ETOR_TEXT": null,
    "AUTO_ETOR": 1708111800000,
    "SPID": "2118990810",
    "fts_flag": "N",
    "geometry_x": -13597640.178199999,
    "geometry_y": 4537548.5891999975
  },
  {
    "F_OUTAGE_ID": 2378360,
    "OUTAGE_EXTENT": "CUSTOMER",
    "OUTAGE_DEVICE_ID": "417498052588",
    "OUTAGE_CIRCUIT_ID": 252051109,
    "CREW_ETA": null,
    "CREW_CURRENT_STATUS": "T-Man Enroute",
    "OUTAGE_CAUSE": null,
    "EST_CUSTOMERS": 1,
    "OUTAGE_LATITUDE": 36.77544,
    "OUTAGE_LONGITUDE": -119.855,
    "CITY": "Fresno",
    "COUNTY": null,
    "ZIP": null,
    "DEVICE_COUNT": 0,
    "OUTAGE_START": 1708094489000,
    "OUTAGE_START_TEXT": null,
    "LAST_UPDATE": 1708094492000,
    "LAST_UPDATE_TEXT": null,
    "CURRENT_ETOR": 1708125300000,
    "CURRENT_ETOR_TEXT": null,
    "AUTO_ETOR": 1708125300000,
    "SPID": "7373400605",
    "fts_flag": "N",
    "geometry_x": -13342197.569,
    "geometry_y": 4407852.070600003
  },
  {
    "F_OUTAGE_ID": 2378361,
    "OUTAGE_EXTENT": "CUSTOMER",
    "OUTAGE_DEVICE_ID": "315421553119",
    "OUTAGE_CIRCUIT_ID": 14302106,
    "CREW_ETA": null,
    "CREW_CURRENT_STATUS": "T-Man Enroute",
    "OUTAGE_CAUSE": null,
    "EST_CUSTOMERS": 1,
    "OUTAGE_LATITUDE": 37.94821,
    "OUTAGE_LONGITUDE": -122.0889,
    "CITY": "Pleasant Hill",
    "COUNTY": null,
    "ZIP": null,
    "DEVICE_COUNT": 0,
    "OUTAGE_START": 1708094501000,
    "OUTAGE_START_TEXT": null,
    "LAST_UPDATE": 1708094502000,
    "LAST_UPDATE_TEXT": null,
    "CURRENT_ETOR": 1708114500000,
    "CURRENT_ETOR_TEXT": null,
    "AUTO_ETOR": 1708114500000,
    "SPID": "1867370505",
    "fts_flag": "N",
    "geometry_x": -13590874.179499999,
    "geometry_y": 4572112.204000004
  },
  {
    "F_OUTAGE_ID": 2378362,
    "OUTAGE_EXTENT": "CUSTOMER",
    "OUTAGE_DEVICE_ID": "219289417721",
    "OUTAGE_CIRCUIT_ID": 42651101,
    "CREW_ETA": null,
    "CREW_CURRENT_STATUS": "T-Man Enroute",
    "OUTAGE_CAUSE": null,
    "EST_CUSTOMERS": 1,
    "OUTAGE_LATITUDE": 38.15317,
    "OUTAGE_LONGITUDE": -122.24837,
    "CITY": "Vallejo",
    "COUNTY": null,
    "ZIP": null,
    "DEVICE_COUNT": 0,
    "OUTAGE_START": 1708094559000,
    "OUTAGE_START_TEXT": null,
    "LAST_UPDATE": 1708094561000,
    "LAST_UPDATE_TEXT": null,
    "CURRENT_ETOR": 1708115400000,
    "CURRENT_ETOR_TEXT": null,
    "AUTO_ETOR": 1708115400000,
    "SPID": "3942795205",
    "fts_flag": "N",
    "geometry_x": -13608626.298700001,
    "geometry_y": 4601086.250799999
  },
  {
    "F_OUTAGE_ID": 2378364,
    "OUTAGE_EXTENT": "CUSTOMER",
    "OUTAGE_DEVICE_ID": "219290224050",
    "OUTAGE_CIRCUIT_ID": 43291105,
    "CREW_ETA": null,
    "CREW_CURRENT_STATUS": "T-Man On Site",
    "OUTAGE_CAUSE": "PATROLLING",
    "EST_CUSTOMERS": 1,
    "OUTAGE_LATITUDE": 38.32661,
    "OUTAGE_LONGITUDE": -122.2487,
    "CITY": "Napa",
    "COUNTY": null,
    "ZIP": null,
    "DEVICE_COUNT": 0,
    "OUTAGE_START": 1708094618000,
    "OUTAGE_START_TEXT": null,
    "LAST_UPDATE": 1708096500000,
    "LAST_UPDATE_TEXT": null,
    "CURRENT_ETOR": 1708130700000,
    "CURRENT_ETOR_TEXT": null,
    "AUTO_ETOR": 1708130700000,
    "SPID": "3353993710",
    "fts_flag": "N",
    "geometry_x": -13608663.0341,
    "geometry_y": 4625668.152900003
  },
  {
    "F_OUTAGE_ID": 2378368,
    "OUTAGE_EXTENT": "CUSTOMER",
    "OUTAGE_DEVICE_ID": "515663760005",
    "OUTAGE_CIRCUIT_ID": 252081101,
    "CREW_ETA": null,
    "CREW_CURRENT_STATUS": "Awaiting T-Man",
    "OUTAGE_CAUSE": null,
    "EST_CUSTOMERS": 1,
    "OUTAGE_LATITUDE": 35.14,
    "OUTAGE_LONGITUDE": -119.45151,
    "CITY": "Taft",
    "COUNTY": null,
    "ZIP": null,
    "DEVICE_COUNT": 0,
    "OUTAGE_START": 1708094848000,
    "OUTAGE_START_TEXT": null,
    "LAST_UPDATE": 1708094852000,
    "LAST_UPDATE_TEXT": null,
    "CURRENT_ETOR": 1708108200000,
    "CURRENT_ETOR_TEXT": null,
    "AUTO_ETOR": 1708108200000,
    "SPID": "7965459305",
    "fts_flag": "N",
    "geometry_x": -13297281.2677,
    "geometry_y": 4182922.898000002
  },
  {
    "F_OUTAGE_ID": 2378373,
    "OUTAGE_EXTENT": "CUSTOMER",
    "OUTAGE_DEVICE_ID": "314645839092",
    "OUTAGE_CIRCUIT_ID": 24060404,
    "CREW_ETA": null,
    "CREW_CURRENT_STATUS": "Awaiting T-Man",
    "OUTAGE_CAUSE": null,
    "EST_CUSTOMERS": 1,
    "OUTAGE_LATITUDE": 37.55909,
    "OUTAGE_LONGITUDE": -122.34828,
    "CITY": "Hillsborough",
    "COUNTY": null,
    "ZIP": null,
    "DEVICE_COUNT": 0,
    "OUTAGE_START": 1708095054000,
    "OUTAGE_START_TEXT": null,
    "LAST_UPDATE": 1708095057000,
    "LAST_UPDATE_TEXT": null,
    "CURRENT_ETOR": 1708131600000,
    "CURRENT_ETOR_TEXT": null,
    "AUTO_ETOR": 1708131600000,
    "SPID": "6160160605",
    "fts_flag": "N",
    "geometry_x": -13619748.229,
    "geometry_y": 4517325.8989999965
  },
  {
    "F_OUTAGE_ID": 2378374,
    "OUTAGE_EXTENT": "CUSTOMER",
    "OUTAGE_DEVICE_ID": "314891047908",
    "OUTAGE_CIRCUIT_ID": 12111108,
    "CREW_ETA": null,
    "CREW_CURRENT_STATUS": "T-Man Enroute",
    "OUTAGE_CAUSE": null,
    "EST_CUSTOMERS": 1,
    "OUTAGE_LATITUDE": 37.80239,
    "OUTAGE_LONGITUDE": -122.26961,
    "CITY": "Oakland",
    "COUNTY": null,
    "ZIP": null,
    "DEVICE_COUNT": 0,
    "OUTAGE_START": 1708095062000,
    "OUTAGE_START_TEXT": null,
    "LAST_UPDATE": 1708095062000,
    "LAST_UPDATE_TEXT": null,
    "CURRENT_ETOR": 1708103700000,
    "CURRENT_ETOR_TEXT": null,
    "AUTO_ETOR": 1708103700000,
    "SPID": "2964173231",
    "fts_flag": "N",
    "geometry_x": -13610990.7247,
    "geometry_y": 4551547.635799997
  },
  {
    "F_OUTAGE_ID": 2378381,
    "OUTAGE_EXTENT": "CUSTOMER",
    "OUTAGE_DEVICE_ID": "220730632148",
    "OUTAGE_CIRCUIT_ID": 62041104,
    "CREW_ETA": null,
    "CREW_CURRENT_STATUS": "Awaiting T-Man",
    "OUTAGE_CAUSE": null,
    "EST_CUSTOMERS": 1,
    "OUTAGE_LATITUDE": 38.54896,
    "OUTAGE_LONGITUDE": -121.74557,
    "CITY": "Davis",
    "COUNTY": null,
    "ZIP": null,
    "DEVICE_COUNT": 0,
    "OUTAGE_START": 1708095398000,
    "OUTAGE_START_TEXT": null,
    "LAST_UPDATE": 1708095400000,
    "LAST_UPDATE_TEXT": null,
    "CURRENT_ETOR": 1708121700000,
    "CURRENT_ETOR_TEXT": null,
    "AUTO_ETOR": 1708121700000,
    "SPID": "5001593305",
    "fts_flag": "N",
    "geometry_x": -13552654.8587,
    "geometry_y": 4657268.3576000035
  },
  {
    "F_OUTAGE_ID": 2378382,
    "OUTAGE_EXTENT": "CUSTOMER",
    "OUTAGE_DEVICE_ID": "316117830051",
    "OUTAGE_CIRCUIT_ID": 83392106,
    "CREW_ETA": null,
    "CREW_CURRENT_STATUS": "Awaiting T-Man",
    "OUTAGE_CAUSE": null,
    "EST_CUSTOMERS": 1,
    "OUTAGE_LATITUDE": 37.31764,
    "OUTAGE_LONGITUDE": -121.83604,
    "CITY": "San Jose",
    "COUNTY": null,
    "ZIP": null,
    "DEVICE_COUNT": 0,
    "OUTAGE_START": 1708095519000,
    "OUTAGE_START_TEXT": null,
    "LAST_UPDATE": 1708095522000,
    "LAST_UPDATE_TEXT": null,
    "CURRENT_ETOR": 1708109100000,
    "CURRENT_ETOR_TEXT": null,
    "AUTO_ETOR": 1708109100000,
    "SPID": "8339124905",
    "fts_flag": "N",
    "geometry_x": -13562725.9331,
    "geometry_y": 4483474.674800001
  },
  {
    "F_OUTAGE_ID": 2378384,
    "OUTAGE_EXTENT": "CUSTOMER",
    "OUTAGE_DEVICE_ID": "317851052919",
    "OUTAGE_CIRCUIT_ID": 163481105,
    "CREW_ETA": null,
    "CREW_CURRENT_STATUS": "Awaiting T-Man",
    "OUTAGE_CAUSE": null,
    "EST_CUSTOMERS": 1,
    "OUTAGE_LATITUDE": 37.95107,
    "OUTAGE_LONGITUDE": -121.24639,
    "CITY": "Stockton",
    "COUNTY": null,
    "ZIP": null,
    "DEVICE_COUNT": 0,
    "OUTAGE_START": 1708095659000,
    "OUTAGE_START_TEXT": null,
    "LAST_UPDATE": 1708095662000,
    "LAST_UPDATE_TEXT": null,
    "CURRENT_ETOR": 1708104600000,
    "CURRENT_ETOR_TEXT": null,
    "AUTO_ETOR": 1708104600000,
    "SPID": "9717578205",
    "fts_flag": "N",
    "geometry_x": -13497086.3953,
    "geometry_y": 4572515.949000001
  },
  {
    "F_OUTAGE_ID": 2378385,
    "OUTAGE_EXTENT": "CUSTOMER",
    "OUTAGE_DEVICE_ID": "516789666736",
    "OUTAGE_CIRCUIT_ID": 254072107,
    "CREW_ETA": null,
    "CREW_CURRENT_STATUS": "Awaiting T-Man",
    "OUTAGE_CAUSE": null,
    "EST_CUSTOMERS": 1,
    "OUTAGE_LATITUDE": 35.32905,
    "OUTAGE_LONGITUDE": -119.07715,
    "CITY": "Bakersfield",
    "COUNTY": null,
    "ZIP": null,
    "DEVICE_COUNT": 0,
    "OUTAGE_START": 1708095759000,
    "OUTAGE_START_TEXT": null,
    "LAST_UPDATE": 1708095764000,
    "LAST_UPDATE_TEXT": null,
    "CURRENT_ETOR": 1708103700000,
    "CURRENT_ETOR_TEXT": null,
    "AUTO_ETOR": 1708103700000,
    "SPID": "6421019605",
    "fts_flag": "N",
    "geometry_x": -13255607.7031,
    "geometry_y": 4208688.1228
  },
  {
    "F_OUTAGE_ID": 2378386,
    "OUTAGE_EXTENT": "CUSTOMER",
    "OUTAGE_DEVICE_ID": "314260747121",
    "OUTAGE_CIRCUIT_ID": 22281102,
    "CREW_ETA": null,
    "CREW_CURRENT_STATUS": "Awaiting T-Man",
    "OUTAGE_CAUSE": null,
    "EST_CUSTOMERS": 1,
    "OUTAGE_LATITUDE": 37.77735,
    "OUTAGE_LONGITUDE": -122.48678,
    "CITY": "San Francisco",
    "COUNTY": null,
    "ZIP": null,
    "DEVICE_COUNT": 0,
    "OUTAGE_START": 1708095900000,
    "OUTAGE_START_TEXT": null,
    "LAST_UPDATE": 1708095917000,
    "LAST_UPDATE_TEXT": null,
    "CURRENT_ETOR": 1708103700000,
    "CURRENT_ETOR_TEXT": null,
    "AUTO_ETOR": 1708103700000,
    "SPID": "6258705810",
    "fts_flag": "N",
    "geometry_x": -13635165.978500001,
    "geometry_y": 4548020.406400003
  },
  {
    "F_OUTAGE_ID": 2378387,
    "OUTAGE_EXTENT": "CUSTOMER",
    "OUTAGE_DEVICE_ID": "315553428591",
    "OUTAGE_CIRCUIT_ID": 83371106,
    "CREW_ETA": null,
    "CREW_CURRENT_STATUS": "Awaiting T-Man",
    "OUTAGE_CAUSE": null,
    "EST_CUSTOMERS": 1,
    "OUTAGE_LATITUDE": 37.27526,
    "OUTAGE_LONGITUDE": -122.02915,
    "CITY": "Saratoga",
    "COUNTY": null,
    "ZIP": null,
    "DEVICE_COUNT": 0,
    "OUTAGE_START": 1708095967000,
    "OUTAGE_START_TEXT": null,
    "LAST_UPDATE": 1708095972000,
    "LAST_UPDATE_TEXT": null,
    "CURRENT_ETOR": 1708122600000,
    "CURRENT_ETOR_TEXT": null,
    "AUTO_ETOR": 1708122600000,
    "SPID": "7937130710",
    "fts_flag": "N",
    "geometry_x": -13584222.8399,
    "geometry_y": 4477544.247500002
  },
  {
    "F_OUTAGE_ID": 2378389,
    "OUTAGE_EXTENT": "CUSTOMER",
    "OUTAGE_DEVICE_ID": "221078753837",
    "OUTAGE_CIRCUIT_ID": 152851104,
    "CREW_ETA": null,
    "CREW_CURRENT_STATUS": "Awaiting T-Man",
    "OUTAGE_CAUSE": null,
    "EST_CUSTOMERS": 1,
    "OUTAGE_LATITUDE": 39.14428,
    "OUTAGE_LONGITUDE": -121.62088,
    "CITY": "Yuba City",
    "COUNTY": null,
    "ZIP": null,
    "DEVICE_COUNT": 0,
    "OUTAGE_START": 1708096080000,
    "OUTAGE_START_TEXT": null,
    "LAST_UPDATE": 1708096086000,
    "LAST_UPDATE_TEXT": null,
    "CURRENT_ETOR": 1708108200000,
    "CURRENT_ETOR_TEXT": null,
    "AUTO_ETOR": 1708108200000,
    "SPID": "1095334210",
    "fts_flag": "N",
    "geometry_x": -13538774.431400001,
    "geometry_y": 4742359.566799998
  },
  {
    "F_OUTAGE_ID": 2378390,
    "OUTAGE_EXTENT": "CUSTOMER",
    "OUTAGE_DEVICE_ID": "418704746449",
    "OUTAGE_CIRCUIT_ID": 254531110,
    "CREW_ETA": null,
    "CREW_CURRENT_STATUS": "Awaiting T-Man",
    "OUTAGE_CAUSE": null,
    "EST_CUSTOMERS": 1,
    "OUTAGE_LATITUDE": 36.60843,
    "OUTAGE_LONGITUDE": -119.44164,
    "CITY": "Reedley",
    "COUNTY": null,
    "ZIP": null,
    "DEVICE_COUNT": 0,
    "OUTAGE_START": 1708096085000,
    "OUTAGE_START_TEXT": null,
    "LAST_UPDATE": 1708096091000,
    "LAST_UPDATE_TEXT": null,
    "CURRENT_ETOR": 1708116300000,
    "CURRENT_ETOR_TEXT": null,
    "AUTO_ETOR": 1708116300000,
    "SPID": "7028305805",
    "fts_flag": "N",
    "geometry_x": -13296182.544300001,
    "geometry_y": 4384666.617200002
  },
  {
    "F_OUTAGE_ID": 2378391,
    "OUTAGE_EXTENT": "CUSTOMER",
    "OUTAGE_DEVICE_ID": "218088121737",
    "OUTAGE_CIRCUIT_ID": 43491101,
    "CREW_ETA": null,
    "CREW_CURRENT_STATUS": "Awaiting T-Man",
    "OUTAGE_CAUSE": null,
    "EST_CUSTOMERS": 1,
    "OUTAGE_LATITUDE": 38.26159,
    "OUTAGE_LONGITUDE": -122.66709,
    "CITY": "Petaluma",
    "COUNTY": null,
    "ZIP": null,
    "DEVICE_COUNT": 0,
    "OUTAGE_START": 1708096088000,
    "OUTAGE_START_TEXT": null,
    "LAST_UPDATE": 1708096092000,
    "LAST_UPDATE_TEXT": null,
    "CURRENT_ETOR": 1708132500000,
    "CURRENT_ETOR_TEXT": null,
    "AUTO_ETOR": 1708132500000,
    "SPID": "3873971505",
    "fts_flag": "N",
    "geometry_x": -13655237.995900001,
    "geometry_y": 4616445.900700003
  },
  {
    "F_OUTAGE_ID": 2378392,
    "OUTAGE_EXTENT": "CUSTOMER",
    "OUTAGE_DEVICE_ID": "315463617135",
    "OUTAGE_CIRCUIT_ID": 83252105,
    "CREW_ETA": null,
    "CREW_CURRENT_STATUS": "Awaiting T-Man",
    "OUTAGE_CAUSE": null,
    "EST_CUSTOMERS": 1,
    "OUTAGE_LATITUDE": 36.95919,
    "OUTAGE_LONGITUDE": -122.05242,
    "CITY": "Santa Cruz",
    "COUNTY": null,
    "ZIP": null,
    "DEVICE_COUNT": 0,
    "OUTAGE_START": 1708096014000,
    "OUTAGE_START_TEXT": null,
    "LAST_UPDATE": 1708096123000,
    "LAST_UPDATE_TEXT": null,
    "CURRENT_ETOR": 1708122600000,
    "CURRENT_ETOR_TEXT": null,
    "AUTO_ETOR": 1708122600000,
    "SPID": "8729894905",
    "fts_flag": "N",
    "geometry_x": -13586813.2445,
    "geometry_y": 4433419.925099999
  },
  {
    "F_OUTAGE_ID": 2378394,
    "OUTAGE_EXTENT": "CUSTOMER",
    "OUTAGE_DEVICE_ID": "317837456514",
    "OUTAGE_CIRCUIT_ID": 163912102,
    "CREW_ETA": null,
    "CREW_CURRENT_STATUS": "T-Man Enroute",
    "OUTAGE_CAUSE": null,
    "EST_CUSTOMERS": 1,
    "OUTAGE_LATITUDE": 38.04973,
    "OUTAGE_LONGITUDE": -121.25207,
    "CITY": "Morada",
    "COUNTY": null,
    "ZIP": null,
    "DEVICE_COUNT": 0,
    "OUTAGE_START": 1708096426000,
    "OUTAGE_START_TEXT": null,
    "LAST_UPDATE": 1708096716000,
    "LAST_UPDATE_TEXT": null,
    "CURRENT_ETOR": 1708109100000,
    "CURRENT_ETOR_TEXT": null,
    "AUTO_ETOR": 1708109100000,
    "SPID": "9860019705",
    "fts_flag": "N",
    "geometry_x": -13497718.690000001,
    "geometry_y": 4586453.377899997
  },
  {
    "F_OUTAGE_ID": 2378395,
    "OUTAGE_EXTENT": "CUSTOMER",
    "OUTAGE_DEVICE_ID": "314895951163",
    "OUTAGE_CIRCUIT_ID": 13700401,
    "CREW_ETA": null,
    "CREW_CURRENT_STATUS": "T-Man Enroute",
    "OUTAGE_CAUSE": null,
    "EST_CUSTOMERS": 1,
    "OUTAGE_LATITUDE": 37.89178,
    "OUTAGE_LONGITUDE": -122.26993,
    "CITY": "Berkeley",
    "COUNTY": null,
    "ZIP": null,
    "DEVICE_COUNT": 0,
    "OUTAGE_START": 1708096630000,
    "OUTAGE_START_TEXT": null,
    "LAST_UPDATE": 1708096635000,
    "LAST_UPDATE_TEXT": null,
    "CURRENT_ETOR": 1708104600000,
    "CURRENT_ETOR_TEXT": null,
    "AUTO_ETOR": 1708104600000,
    "SPID": "2972905910",
    "fts_flag": "N",
    "geometry_x": -13611026.346900001,
    "geometry_y": 4564149.216300003
  },
  {
    "F_OUTAGE_ID": 2378396,
    "OUTAGE_EXTENT": "CUSTOMER",
    "OUTAGE_DEVICE_ID": "315626732077",
    "OUTAGE_CIRCUIT_ID": 83611112,
    "CREW_ETA": null,
    "CREW_CURRENT_STATUS": "Awaiting T-Man",
    "OUTAGE_CAUSE": null,
    "EST_CUSTOMERS": 1,
    "OUTAGE_LATITUDE": 37.37135,
    "OUTAGE_LONGITUDE": -122.00568,
    "CITY": "Sunnyvale",
    "COUNTY": null,
    "ZIP": null,
    "DEVICE_COUNT": 0,
    "OUTAGE_START": 1708096656000,
    "OUTAGE_START_TEXT": null,
    "LAST_UPDATE": 1708096875000,
    "LAST_UPDATE_TEXT": null,
    "CURRENT_ETOR": 1708122600000,
    "CURRENT_ETOR_TEXT": null,
    "AUTO_ETOR": 1708122600000,
    "SPID": "6314389605",
    "fts_flag": "N",
    "geometry_x": -13581610.171500001,
    "geometry_y": 4490995.367200002
  },
  {
    "F_OUTAGE_ID": 2378397,
    "OUTAGE_EXTENT": "CUSTOMER",
    "OUTAGE_DEVICE_ID": "315844129693",
    "OUTAGE_CIRCUIT_ID": 82921107,
    "CREW_ETA": null,
    "CREW_CURRENT_STATUS": "Awaiting T-Man",
    "OUTAGE_CAUSE": null,
    "EST_CUSTOMERS": 1,
    "OUTAGE_LATITUDE": 37.30655,
    "OUTAGE_LONGITUDE": -121.92992,
    "CITY": "San Jose",
    "COUNTY": null,
    "ZIP": null,
    "DEVICE_COUNT": 0,
    "OUTAGE_START": 1708096742000,
    "OUTAGE_START_TEXT": null,
    "LAST_UPDATE": 1708096744000,
    "LAST_UPDATE_TEXT": null,
    "CURRENT_ETOR": 1708107300000,
    "CURRENT_ETOR_TEXT": null,
    "AUTO_ETOR": 1708107300000,
    "SPID": "8409321605",
    "fts_flag": "N",
    "geometry_x": -13573176.6069,
    "geometry_y": 4481922.477499999
  },
  {
    "F_OUTAGE_ID": 2378398,
    "OUTAGE_EXTENT": "CUSTOMER",
    "OUTAGE_DEVICE_ID": "224145236045",
    "OUTAGE_CIRCUIT_ID": 153662102,
    "CREW_ETA": null,
    "CREW_CURRENT_STATUS": "Awaiting T-Man",
    "OUTAGE_CAUSE": null,
    "EST_CUSTOMERS": 1,
    "OUTAGE_LATITUDE": 38.64803,
    "OUTAGE_LONGITUDE": -120.54919,
    "CITY": "Somerset",
    "COUNTY": null,
    "ZIP": null,
    "DEVICE_COUNT": 0,
    "OUTAGE_START": 1708096753000,
    "OUTAGE_START_TEXT": null,
    "LAST_UPDATE": 1708096755000,
    "LAST_UPDATE_TEXT": null,
    "CURRENT_ETOR": 1708117200000,
    "CURRENT_ETOR_TEXT": null,
    "AUTO_ETOR": 1708117200000,
    "SPID": "1431551305",
    "fts_flag": "N",
    "geometry_x": -13419474.4463,
    "geometry_y": 4671379.5603
  },
  {
    "F_OUTAGE_ID": 2378399,
    "OUTAGE_EXTENT": "CUSTOMER",
    "OUTAGE_DEVICE_ID": "315103234767",
    "OUTAGE_CIRCUIT_ID": 24130401,
    "CREW_ETA": null,
    "CREW_CURRENT_STATUS": "Awaiting T-Man",
    "OUTAGE_CAUSE": null,
    "EST_CUSTOMERS": 1,
    "OUTAGE_LATITUDE": 37.44272,
    "OUTAGE_LONGITUDE": -122.18781,
    "CITY": "Menlo Park",
    "COUNTY": null,
    "ZIP": null,
    "DEVICE_COUNT": 0,
    "OUTAGE_START": 1708096773000,
    "OUTAGE_START_TEXT": null,
    "LAST_UPDATE": 1708096778000,
    "LAST_UPDATE_TEXT": null,
    "CURRENT_ETOR": 1708112700000,
    "CURRENT_ETOR_TEXT": null,
    "AUTO_ETOR": 1708112700000,
    "SPID": "6465406205",
    "fts_flag": "N",
    "geometry_x": -13601884.7903,
    "geometry_y": 4500997.221299998
  },
  {
    "F_OUTAGE_ID": 2378400,
    "OUTAGE_EXTENT": "CUSTOMER",
    "OUTAGE_DEVICE_ID": "100000029782",
    "OUTAGE_CIRCUIT_ID": 163451701,
    "CREW_ETA": null,
    "CREW_CURRENT_STATUS": "Awaiting T-Man",
    "OUTAGE_CAUSE": null,
    "EST_CUSTOMERS": 1,
    "OUTAGE_LATITUDE": 38.14082,
    "OUTAGE_LONGITUDE": -120.45646,
    "CITY": "Murphys",
    "COUNTY": null,
    "ZIP": null,
    "DEVICE_COUNT": 0,
    "OUTAGE_START": 1708096740000,
    "OUTAGE_START_TEXT": null,
    "LAST_UPDATE": 1708096801000,
    "LAST_UPDATE_TEXT": null,
    "CURRENT_ETOR": 1708107300000,
    "CURRENT_ETOR_TEXT": null,
    "AUTO_ETOR": 1708107300000,
    "SPID": "7730769347",
    "fts_flag": "N",
    "geometry_x": -13409151.79,
    "geometry_y": 4599338.100199997
  },
  {
    "F_OUTAGE_ID": 2378402,
    "OUTAGE_EXTENT": "CUSTOMER",
    "OUTAGE_DEVICE_ID": "315584050699",
    "OUTAGE_CIRCUIT_ID": 13532110,
    "CREW_ETA": null,
    "CREW_CURRENT_STATUS": "Awaiting T-Man",
    "OUTAGE_CAUSE": null,
    "EST_CUSTOMERS": 1,
    "OUTAGE_LATITUDE": 37.88241,
    "OUTAGE_LONGITUDE": -122.03127,
    "CITY": "San Miguel-Walnut Creek",
    "COUNTY": null,
    "ZIP": null,
    "DEVICE_COUNT": 0,
    "OUTAGE_START": 1708096941000,
    "OUTAGE_START_TEXT": null,
    "LAST_UPDATE": 1708096943000,
    "LAST_UPDATE_TEXT": null,
    "CURRENT_ETOR": 1708133400000,
    "CURRENT_ETOR_TEXT": null,
    "AUTO_ETOR": 1708133400000,
    "SPID": "1955315405",
    "fts_flag": "N",
    "geometry_x": -13584458.837299999,
    "geometry_y": 4562827.581699997
  },
  {
    "F_OUTAGE_ID": 2378403,
    "OUTAGE_EXTENT": "CUSTOMER",
    "OUTAGE_DEVICE_ID": "315704836772",
    "OUTAGE_CIRCUIT_ID": 12221107,
    "CREW_ETA": null,
    "CREW_CURRENT_STATUS": "Awaiting T-Man",
    "OUTAGE_CAUSE": null,
    "EST_CUSTOMERS": 1,
    "OUTAGE_LATITUDE": 37.50044,
    "OUTAGE_LONGITUDE": -121.98139,
    "CITY": "Fremont",
    "COUNTY": null,
    "ZIP": null,
    "DEVICE_COUNT": 0,
    "OUTAGE_START": 1708096960000,
    "OUTAGE_START_TEXT": null,
    "LAST_UPDATE": 1708096963000,
    "LAST_UPDATE_TEXT": null,
    "CURRENT_ETOR": 1708128000000,
    "CURRENT_ETOR_TEXT": null,
    "AUTO_ETOR": 1708128000000,
    "SPID": "7971749341",
    "fts_flag": "N",
    "geometry_x": -13578906.221099999,
    "geometry_y": 4509093.131899998
  },
  {
    "F_OUTAGE_ID": 2378404,
    "OUTAGE_EXTENT": "CUSTOMER",
    "OUTAGE_DEVICE_ID": "223552926135",
    "OUTAGE_CIRCUIT_ID": 163751101,
    "CREW_ETA": null,
    "CREW_CURRENT_STATUS": "Awaiting T-Man",
    "OUTAGE_CAUSE": null,
    "EST_CUSTOMERS": 1,
    "OUTAGE_LATITUDE": 38.37775,
    "OUTAGE_LONGITUDE": -120.76159,
    "CITY": "Jackson",
    "COUNTY": null,
    "ZIP": null,
    "DEVICE_COUNT": 0,
    "OUTAGE_START": 1708097083000,
    "OUTAGE_START_TEXT": null,
    "LAST_UPDATE": 1708097084000,
    "LAST_UPDATE_TEXT": null,
    "CURRENT_ETOR": 1708110900000,
    "CURRENT_ETOR_TEXT": null,
    "AUTO_ETOR": 1708110900000,
    "SPID": "9223094405",
    "fts_flag": "N",
    "geometry_x": -13443118.7062,
    "geometry_y": 4632927.519100003
  }
]
