[
  {
    "F_OUTAGE_ID": 2337372,
    "OUTAGE_EXTENT": "CUSTOMER",
    "OUTAGE_DEVICE_ID": "218498225472",
    "OUTAGE_CIRCUIT_ID": 43071102,
    "CREW_ETA": null,
    "CREW_CURRENT_STATUS": "Awaiting Crew",
    "OUTAGE_CAUSE": "REPLCE SRVC",
    "EST_CUSTOMERS": 1,
    "OUTAGE_LATITUDE": 38.36522,
    "OUTAGE_LONGITUDE": -122.52445,
    "CITY": "Glen Ellen",
    "COUNTY": null,
    "ZIP": null,
    "DEVICE_COUNT": 0,
    "OUTAGE_START": 1707043138000,
    "OUTAGE_START_TEXT": null,
    "LAST_UPDATE": 1707602097000,
    "LAST_UPDATE_TEXT": null,
    "CURRENT_ETOR": 1707688800000,
    "CURRENT_ETOR_TEXT": null,
    "AUTO_ETOR": null,
    "SPID": "3836232005",
    "fts_flag": "N",
    "geometry_x": -13639359.3837,
    "geometry_y": 4631148.400700003
  },
  {
    "F_OUTAGE_ID": 2346040,
    "OUTAGE_EXTENT": "CUSTOMER",
    "OUTAGE_DEVICE_ID": "217958928039",
    "OUTAGE_CIRCUIT_ID": 42151108,
    "CREW_ETA": null,
    "CREW_CURRENT_STATUS": "Awaiting Crew",
    "OUTAGE_CAUSE": "TREE CONTACT",
    "EST_CUSTOMERS": 1,
    "OUTAGE_LATITUDE": 38.43416,
    "OUTAGE_LONGITUDE": -122.71372,
    "CITY": "Santa Rosa",
    "COUNTY": null,
    "ZIP": null,
    "DEVICE_COUNT": 0,
    "OUTAGE_START": 1707063682000,
    "OUTAGE_START_TEXT": null,
    "LAST_UPDATE": 1707597748000,
    "LAST_UPDATE_TEXT": null,
    "CURRENT_ETOR": 1707681600000,
    "CURRENT_ETOR_TEXT": null,
    "AUTO_ETOR": null,
    "SPID": "4167214710",
    "fts_flag": "N",
    "geometry_x": -13660428.8237,
    "geometry_y": 4640940.920699999
  },
  {
    "F_OUTAGE_ID": 2360344,
    "OUTAGE_EXTENT": "CUSTOMER",
    "OUTAGE_DEVICE_ID": "217141441083",
    "OUTAGE_CIRCUIT_ID": 42821102,
    "CREW_ETA": null,
    "CREW_CURRENT_STATUS": "Awaiting Crew",
    "OUTAGE_CAUSE": "REPAIR WIRE DWN",
    "EST_CUSTOMERS": 1,
    "OUTAGE_LATITUDE": 38.79025,
    "OUTAGE_LONGITUDE": -123.00369,
    "CITY": "Cloverdale",
    "COUNTY": null,
    "ZIP": null,
    "DEVICE_COUNT": 0,
    "OUTAGE_START": 1707143656000,
    "OUTAGE_START_TEXT": null,
    "LAST_UPDATE": 1707597689000,
    "LAST_UPDATE_TEXT": null,
    "CURRENT_ETOR": 1707681600000,
    "CURRENT_ETOR_TEXT": null,
    "AUTO_ETOR": null,
    "SPID": "3369465405",
    "fts_flag": "N",
    "geometry_x": -13692708.136500001,
    "geometry_y": 4691671.063900001
  },
  {
    "F_OUTAGE_ID": 2362574,
    "OUTAGE_EXTENT": "CUSTOMER",
    "OUTAGE_DEVICE_ID": "216998824635",
    "OUTAGE_CIRCUIT_ID": 43161101,
    "CREW_ETA": null,
    "CREW_CURRENT_STATUS": "Awaiting Crew",
    "OUTAGE_CAUSE": "REPLCE SRVC",
    "EST_CUSTOMERS": 1,
    "OUTAGE_LATITUDE": 38.3383,
    "OUTAGE_LONGITUDE": -123.04742,
    "CITY": "Bodega Bay",
    "COUNTY": null,
    "ZIP": null,
    "DEVICE_COUNT": 0,
    "OUTAGE_START": 1707173040000,
    "OUTAGE_START_TEXT": null,
    "LAST_UPDATE": 1707602118000,
    "LAST_UPDATE_TEXT": null,
    "CURRENT_ETOR": 1707688800000,
    "CURRENT_ETOR_TEXT": null,
    "AUTO_ETOR": null,
    "SPID": "4080445605",
    "fts_flag": "N",
    "geometry_x": -13697576.1378,
    "geometry_y": 4627327.106399998
  },
  {
    "F_OUTAGE_ID": 2363160,
    "OUTAGE_EXTENT": "CUSTOMER",
    "OUTAGE_DEVICE_ID": "217662925491",
    "OUTAGE_CIRCUIT_ID": 42571104,
    "CREW_ETA": null,
    "CREW_CURRENT_STATUS": "Awaiting Crew",
    "OUTAGE_CAUSE": "REPLCE SRVC",
    "EST_CUSTOMERS": 1,
    "OUTAGE_LATITUDE": 38.3638,
    "OUTAGE_LONGITUDE": -122.81641,
    "CITY": "Sebastopol",
    "COUNTY": null,
    "ZIP": null,
    "DEVICE_COUNT": 0,
    "OUTAGE_START": 1707203963000,
    "OUTAGE_START_TEXT": null,
    "LAST_UPDATE": 1707601561000,
    "LAST_UPDATE_TEXT": null,
    "CURRENT_ETOR": 1707688800000,
    "CURRENT_ETOR_TEXT": null,
    "AUTO_ETOR": null,
    "SPID": "4445792710",
    "fts_flag": "N",
    "geometry_x": -13671860.2223,
    "geometry_y": 4630946.7962
  },
  {
    "F_OUTAGE_ID": 2363753,
    "OUTAGE_EXTENT": "CUSTOMER",
    "OUTAGE_DEVICE_ID": "217967323885",
    "OUTAGE_CIRCUIT_ID": 42271104,
    "CREW_ETA": null,
    "CREW_CURRENT_STATUS": "Awaiting Crew",
    "OUTAGE_CAUSE": "REPLCE SRVC",
    "EST_CUSTOMERS": 1,
    "OUTAGE_LATITUDE": 38.32032,
    "OUTAGE_LONGITUDE": -122.7097,
    "CITY": "Cotati",
    "COUNTY": null,
    "ZIP": null,
    "DEVICE_COUNT": 0,
    "OUTAGE_START": 1707213220000,
    "OUTAGE_START_TEXT": null,
    "LAST_UPDATE": 1707601522000,
    "LAST_UPDATE_TEXT": null,
    "CURRENT_ETOR": 1707688800000,
    "CURRENT_ETOR_TEXT": null,
    "AUTO_ETOR": null,
    "SPID": "4207526105",
    "fts_flag": "N",
    "geometry_x": -13659981.319400001,
    "geometry_y": 4624775.636
  },
  {
    "F_OUTAGE_ID": 2364369,
    "OUTAGE_EXTENT": "CUSTOMER",
    "OUTAGE_DEVICE_ID": "215159445877",
    "OUTAGE_CIRCUIT_ID": 43381101,
    "CREW_ETA": null,
    "CREW_CURRENT_STATUS": "Awaiting Crew",
    "OUTAGE_CAUSE": "REPLCE SRVC",
    "EST_CUSTOMERS": 1,
    "OUTAGE_LATITUDE": 38.9139,
    "OUTAGE_LONGITUDE": -123.70261,
    "CITY": "Point Arena",
    "COUNTY": null,
    "ZIP": null,
    "DEVICE_COUNT": 0,
    "OUTAGE_START": 1707223178000,
    "OUTAGE_START_TEXT": null,
    "LAST_UPDATE": 1707627745000,
    "LAST_UPDATE_TEXT": null,
    "CURRENT_ETOR": 1707775200000,
    "CURRENT_ETOR_TEXT": null,
    "AUTO_ETOR": null,
    "SPID": "3529758305",
    "fts_flag": "N",
    "geometry_x": -13770511.555,
    "geometry_y": 4709345.979599997
  },
  {
    "F_OUTAGE_ID": 2367633,
    "OUTAGE_EXTENT": "CUSTOMER",
    "OUTAGE_DEVICE_ID": "216894231643",
    "OUTAGE_CIRCUIT_ID": 42811111,
    "CREW_ETA": "2/10/2024 10:30:00 PM",
    "CREW_CURRENT_STATUS": "Awaiting Crew",
    "OUTAGE_CAUSE": "REPLCE SRVC",
    "EST_CUSTOMERS": 1,
    "OUTAGE_LATITUDE": 38.53326,
    "OUTAGE_LONGITUDE": -123.08651,
    "CITY": "Cazadero",
    "COUNTY": null,
    "ZIP": null,
    "DEVICE_COUNT": 0,
    "OUTAGE_START": 1707315578000,
    "OUTAGE_START_TEXT": null,
    "LAST_UPDATE": 1707596199000,
    "LAST_UPDATE_TEXT": null,
    "CURRENT_ETOR": 1707652800000,
    "CURRENT_ETOR_TEXT": null,
    "AUTO_ETOR": null,
    "SPID": "3454893805",
    "fts_flag": "N",
    "geometry_x": -13701927.616700001,
    "geometry_y": 4655033.887500003
  },
  {
    "F_OUTAGE_ID": 2367810,
    "OUTAGE_EXTENT": "CUSTOMER",
    "OUTAGE_DEVICE_ID": "215884250959",
    "OUTAGE_CIRCUIT_ID": 42601102,
    "CREW_ETA": null,
    "CREW_CURRENT_STATUS": "Awaiting Crew",
    "OUTAGE_CAUSE": "REPAIR WIRE DWN",
    "EST_CUSTOMERS": 1,
    "OUTAGE_LATITUDE": 39.05753,
    "OUTAGE_LONGITUDE": -123.4508,
    "CITY": "Philo",
    "COUNTY": null,
    "ZIP": null,
    "DEVICE_COUNT": 0,
    "OUTAGE_START": 1707317853000,
    "OUTAGE_START_TEXT": null,
    "LAST_UPDATE": 1707620906000,
    "LAST_UPDATE_TEXT": null,
    "CURRENT_ETOR": 1707652800000,
    "CURRENT_ETOR_TEXT": null,
    "AUTO_ETOR": null,
    "SPID": "4448946767",
    "fts_flag": "N",
    "geometry_x": -13742480.194,
    "geometry_y": 4729915.6049000025
  },
  {
    "F_OUTAGE_ID": 2367835,
    "OUTAGE_EXTENT": "CUSTOMER",
    "OUTAGE_DEVICE_ID": "217147530621",
    "OUTAGE_CIRCUIT_ID": 42811113,
    "CREW_ETA": null,
    "CREW_CURRENT_STATUS": "Awaiting Crew",
    "OUTAGE_CAUSE": "REPAIR WIRE DWN",
    "EST_CUSTOMERS": 1,
    "OUTAGE_LATITUDE": 38.50291,
    "OUTAGE_LONGITUDE": -122.99746,
    "CITY": "Guerneville",
    "COUNTY": null,
    "ZIP": null,
    "DEVICE_COUNT": 0,
    "OUTAGE_START": 1707318379000,
    "OUTAGE_START_TEXT": null,
    "LAST_UPDATE": 1707597748000,
    "LAST_UPDATE_TEXT": null,
    "CURRENT_ETOR": 1707681600000,
    "CURRENT_ETOR_TEXT": null,
    "AUTO_ETOR": null,
    "SPID": "3601198705",
    "fts_flag": "N",
    "geometry_x": -13692014.6161,
    "geometry_y": 4650715.768399999
  },
  {
    "F_OUTAGE_ID": 2370741,
    "OUTAGE_EXTENT": "CUSTOMER",
    "OUTAGE_DEVICE_ID": "217202631339",
    "OUTAGE_CIRCUIT_ID": 42811113,
    "CREW_ETA": null,
    "CREW_CURRENT_STATUS": "Awaiting Crew",
    "OUTAGE_CAUSE": "REPLCE SRVC",
    "EST_CUSTOMERS": 1,
    "OUTAGE_LATITUDE": 38.52294,
    "OUTAGE_LONGITUDE": -122.97872,
    "CITY": "Guerneville",
    "COUNTY": null,
    "ZIP": null,
    "DEVICE_COUNT": 0,
    "OUTAGE_START": 1707414042000,
    "OUTAGE_START_TEXT": null,
    "LAST_UPDATE": 1707601690000,
    "LAST_UPDATE_TEXT": null,
    "CURRENT_ETOR": 1707688800000,
    "CURRENT_ETOR_TEXT": null,
    "AUTO_ETOR": null,
    "SPID": "3496972605",
    "fts_flag": "N",
    "geometry_x": -13689928.4888,
    "geometry_y": 4653565.380400002
  },
  {
    "F_OUTAGE_ID": 2371596,
    "OUTAGE_EXTENT": "CUSTOMER",
    "OUTAGE_DEVICE_ID": "218936537724",
    "OUTAGE_CIRCUIT_ID": 43432104,
    "CREW_ETA": null,
    "CREW_CURRENT_STATUS": "Awaiting Crew",
    "OUTAGE_CAUSE": "REPLCE TXFMR",
    "EST_CUSTOMERS": 1,
    "OUTAGE_LATITUDE": 38.70169,
    "OUTAGE_LONGITUDE": -122.37385,
    "CITY": "Pope Valley",
    "COUNTY": null,
    "ZIP": null,
    "DEVICE_COUNT": 0,
    "OUTAGE_START": 1707476447000,
    "OUTAGE_START_TEXT": null,
    "LAST_UPDATE": 1707587288000,
    "LAST_UPDATE_TEXT": null,
    "CURRENT_ETOR": 1707688800000,
    "CURRENT_ETOR_TEXT": null,
    "AUTO_ETOR": null,
    "SPID": "3458949379",
    "fts_flag": "N",
    "geometry_x": -13622594.6684,
    "geometry_y": 4679030.8587
  },
  {
    "F_OUTAGE_ID": 2372558,
    "OUTAGE_EXTENT": "CUSTOMER",
    "OUTAGE_DEVICE_ID": "316134327356",
    "OUTAGE_CIRCUIT_ID": 82952113,
    "CREW_ETA": null,
    "CREW_CURRENT_STATUS": "Awaiting Crew",
    "OUTAGE_CAUSE": "DAMGE UG CABLE",
    "EST_CUSTOMERS": 1,
    "OUTAGE_LATITUDE": 37.24372,
    "OUTAGE_LONGITUDE": -121.82909,
    "CITY": "San Jose",
    "COUNTY": null,
    "ZIP": null,
    "DEVICE_COUNT": 0,
    "OUTAGE_START": 1707557940000,
    "OUTAGE_START_TEXT": null,
    "LAST_UPDATE": 1707579551000,
    "LAST_UPDATE_TEXT": null,
    "CURRENT_ETOR": 1707692400000,
    "CURRENT_ETOR_TEXT": null,
    "AUTO_ETOR": null,
    "SPID": "8434573405",
    "fts_flag": "N",
    "geometry_x": -13561952.262600001,
    "geometry_y": 4473132.877800003
  },
  {
    "F_OUTAGE_ID": 2372656,
    "OUTAGE_EXTENT": "CUSTOMER",
    "OUTAGE_DEVICE_ID": "314888432661",
    "OUTAGE_CIRCUIT_ID": 24251101,
    "CREW_ETA": null,
    "CREW_CURRENT_STATUS": "Crew Enroute",
    "OUTAGE_CAUSE": "DAMGE UG CABLE",
    "EST_CUSTOMERS": 1,
    "OUTAGE_LATITUDE": 37.38384,
    "OUTAGE_LONGITUDE": -122.26045,
    "CITY": "Woodside",
    "COUNTY": null,
    "ZIP": null,
    "DEVICE_COUNT": 0,
    "OUTAGE_START": 1707562227000,
    "OUTAGE_START_TEXT": null,
    "LAST_UPDATE": 1707625348000,
    "LAST_UPDATE_TEXT": null,
    "CURRENT_ETOR": 1707634800000,
    "CURRENT_ETOR_TEXT": null,
    "AUTO_ETOR": null,
    "SPID": "6380915805",
    "fts_flag": "N",
    "geometry_x": -13609971.0382,
    "geometry_y": 4492745.039099999
  },
  {
    "F_OUTAGE_ID": 2372704,
    "OUTAGE_EXTENT": "CUSTOMER",
    "OUTAGE_DEVICE_ID": "314727439358",
    "OUTAGE_CIRCUIT_ID": 24011104,
    "CREW_ETA": null,
    "CREW_CURRENT_STATUS": "Awaiting Crew",
    "OUTAGE_CAUSE": "NG CONNECTION",
    "EST_CUSTOMERS": 1,
    "OUTAGE_LATITUDE": 37.56685,
    "OUTAGE_LONGITUDE": -122.32034,
    "CITY": "San Mateo",
    "COUNTY": null,
    "ZIP": null,
    "DEVICE_COUNT": 0,
    "OUTAGE_START": 1707565512000,
    "OUTAGE_START_TEXT": null,
    "LAST_UPDATE": 1707618025000,
    "LAST_UPDATE_TEXT": null,
    "CURRENT_ETOR": 1707665400000,
    "CURRENT_ETOR_TEXT": null,
    "AUTO_ETOR": null,
    "SPID": "6261766905",
    "fts_flag": "N",
    "geometry_x": -13616637.9625,
    "geometry_y": 4518415.6642
  },
  {
    "F_OUTAGE_ID": 2372717,
    "OUTAGE_EXTENT": "CUSTOMER",
    "OUTAGE_DEVICE_ID": "314922635934",
    "OUTAGE_CIRCUIT_ID": 24181103,
    "CREW_ETA": null,
    "CREW_CURRENT_STATUS": "Awaiting Crew",
    "OUTAGE_CAUSE": "REPLCE SRVC",
    "EST_CUSTOMERS": 1,
    "OUTAGE_LATITUDE": 37.47388,
    "OUTAGE_LONGITUDE": -122.25081,
    "CITY": "Redwood City",
    "COUNTY": null,
    "ZIP": null,
    "DEVICE_COUNT": 0,
    "OUTAGE_START": 1707566091000,
    "OUTAGE_START_TEXT": null,
    "LAST_UPDATE": 1707602131000,
    "LAST_UPDATE_TEXT": null,
    "CURRENT_ETOR": 1707663600000,
    "CURRENT_ETOR_TEXT": null,
    "AUTO_ETOR": null,
    "SPID": "6693812305",
    "fts_flag": "N",
    "geometry_x": -13608897.9183,
    "geometry_y": 4505367.0022
  },
  {
    "F_OUTAGE_ID": 2372772,
    "OUTAGE_EXTENT": "CUSTOMER",
    "OUTAGE_DEVICE_ID": "513589840975",
    "OUTAGE_CIRCUIT_ID": 182721102,
    "CREW_ETA": null,
    "CREW_CURRENT_STATUS": "Awaiting Crew",
    "OUTAGE_CAUSE": "DAMGE UG CABLE",
    "EST_CUSTOMERS": 1,
    "OUTAGE_LATITUDE": 34.60728,
    "OUTAGE_LONGITUDE": -120.13154,
    "CITY": "Solvang",
    "COUNTY": null,
    "ZIP": null,
    "DEVICE_COUNT": 0,
    "OUTAGE_START": 1707570611000,
    "OUTAGE_START_TEXT": null,
    "LAST_UPDATE": 1707592215000,
    "LAST_UPDATE_TEXT": null,
    "CURRENT_ETOR": null,
    "CURRENT_ETOR_TEXT": null,
    "AUTO_ETOR": null,
    "SPID": "529127305",
    "fts_flag": "N",
    "geometry_x": -13372981.861,
    "geometry_y": 4110639.3109000027
  },
  {
    "F_OUTAGE_ID": 2372784,
    "OUTAGE_EXTENT": "CUSTOMER",
    "OUTAGE_DEVICE_ID": "315776122340",
    "OUTAGE_CIRCUIT_ID": 82021107,
    "CREW_ETA": null,
    "CREW_CURRENT_STATUS": "Awaiting Crew",
    "OUTAGE_CAUSE": "STORM",
    "EST_CUSTOMERS": 1,
    "OUTAGE_LATITUDE": 37.10456,
    "OUTAGE_LONGITUDE": -121.94961,
    "CITY": "Los Gatos",
    "COUNTY": null,
    "ZIP": null,
    "DEVICE_COUNT": 0,
    "OUTAGE_START": 1707572365000,
    "OUTAGE_START_TEXT": null,
    "LAST_UPDATE": 1707583033000,
    "LAST_UPDATE_TEXT": null,
    "CURRENT_ETOR": null,
    "CURRENT_ETOR_TEXT": null,
    "AUTO_ETOR": null,
    "SPID": "8017076305",
    "fts_flag": "N",
    "geometry_x": -13575368.487599999,
    "geometry_y": 4453691.141199999
  },
  {
    "F_OUTAGE_ID": 2372839,
    "OUTAGE_EXTENT": "CUSTOMER",
    "OUTAGE_DEVICE_ID": "216894231643",
    "OUTAGE_CIRCUIT_ID": 42811111,
    "CREW_ETA": null,
    "CREW_CURRENT_STATUS": "Awaiting Crew",
    "OUTAGE_CAUSE": "REPAIR WIRE DWN",
    "EST_CUSTOMERS": 1,
    "OUTAGE_LATITUDE": 38.53326,
    "OUTAGE_LONGITUDE": -123.08651,
    "CITY": "Cazadero",
    "COUNTY": null,
    "ZIP": null,
    "DEVICE_COUNT": 0,
    "OUTAGE_START": 1707576599000,
    "OUTAGE_START_TEXT": null,
    "LAST_UPDATE": 1707593297000,
    "LAST_UPDATE_TEXT": null,
    "CURRENT_ETOR": null,
    "CURRENT_ETOR_TEXT": null,
    "AUTO_ETOR": null,
    "SPID": "3434043805",
    "fts_flag": "N",
    "geometry_x": -13701927.616700001,
    "geometry_y": 4655033.887500003
  },
  {
    "F_OUTAGE_ID": 2372935,
    "OUTAGE_EXTENT": "CUSTOMER",
    "OUTAGE_DEVICE_ID": "412020846379",
    "OUTAGE_CIRCUIT_ID": 182731101,
    "CREW_ETA": null,
    "CREW_CURRENT_STATUS": "Awaiting Crew",
    "OUTAGE_CAUSE": "REPLCE SRVC",
    "EST_CUSTOMERS": 1,
    "OUTAGE_LATITUDE": 36.57609,
    "OUTAGE_LONGITUDE": -121.71927,
    "CITY": "Salinas",
    "COUNTY": null,
    "ZIP": null,
    "DEVICE_COUNT": 0,
    "OUTAGE_START": 1707584987000,
    "OUTAGE_START_TEXT": null,
    "LAST_UPDATE": 1707587720000,
    "LAST_UPDATE_TEXT": null,
    "CURRENT_ETOR": null,
    "CURRENT_ETOR_TEXT": null,
    "AUTO_ETOR": null,
    "SPID": "350376705",
    "fts_flag": "N",
    "geometry_x": -13549727.156100001,
    "geometry_y": 4380182.769500002
  },
  {
    "F_OUTAGE_ID": 2372938,
    "OUTAGE_EXTENT": "CUSTOMER",
    "OUTAGE_DEVICE_ID": "513654541269",
    "OUTAGE_CIRCUIT_ID": 182721101,
    "CREW_ETA": null,
    "CREW_CURRENT_STATUS": "Awaiting Crew",
    "OUTAGE_CAUSE": "REPLCE SRVC",
    "EST_CUSTOMERS": 1,
    "OUTAGE_LATITUDE": 34.61568,
    "OUTAGE_LONGITUDE": -120.11,
    "CITY": "Santa Ynez",
    "COUNTY": null,
    "ZIP": null,
    "DEVICE_COUNT": 0,
    "OUTAGE_START": 1707585240000,
    "OUTAGE_START_TEXT": null,
    "LAST_UPDATE": 1707606847000,
    "LAST_UPDATE_TEXT": null,
    "CURRENT_ETOR": null,
    "CURRENT_ETOR_TEXT": null,
    "AUTO_ETOR": null,
    "SPID": "632905905",
    "fts_flag": "N",
    "geometry_x": -13370584.0392,
    "geometry_y": 4111775.4689000025
  },
  {
    "F_OUTAGE_ID": 2373013,
    "OUTAGE_EXTENT": "CUSTOMER",
    "OUTAGE_DEVICE_ID": "316207434136",
    "OUTAGE_CIRCUIT_ID": 82831109,
    "CREW_ETA": null,
    "CREW_CURRENT_STATUS": "Awaiting Crew",
    "OUTAGE_CAUSE": "STORM",
    "EST_CUSTOMERS": 1,
    "OUTAGE_LATITUDE": 37.43055,
    "OUTAGE_LONGITUDE": -121.80729,
    "CITY": "San Jose",
    "COUNTY": null,
    "ZIP": null,
    "DEVICE_COUNT": 0,
    "OUTAGE_START": 1707594420000,
    "OUTAGE_START_TEXT": null,
    "LAST_UPDATE": 1707616033000,
    "LAST_UPDATE_TEXT": null,
    "CURRENT_ETOR": null,
    "CURRENT_ETOR_TEXT": null,
    "AUTO_ETOR": null,
    "SPID": "8627217105",
    "fts_flag": "N",
    "geometry_x": -13559525.4977,
    "geometry_y": 4499291.032799996
  },
  {
    "F_OUTAGE_ID": 2373032,
    "OUTAGE_EXTENT": "CUSTOMER",
    "OUTAGE_DEVICE_ID": "314964255938",
    "OUTAGE_CIRCUIT_ID": 13921104,
    "CREW_ETA": null,
    "CREW_CURRENT_STATUS": "Awaiting Crew",
    "OUTAGE_CAUSE": "PATROLLING",
    "EST_CUSTOMERS": 1,
    "OUTAGE_LATITUDE": 38.02339,
    "OUTAGE_LONGITUDE": -122.24932,
    "CITY": "Rodeo",
    "COUNTY": null,
    "ZIP": null,
    "DEVICE_COUNT": 0,
    "OUTAGE_START": 1707599789000,
    "OUTAGE_START_TEXT": null,
    "LAST_UPDATE": 1707630560000,
    "LAST_UPDATE_TEXT": null,
    "CURRENT_ETOR": 1707641100000,
    "CURRENT_ETOR_TEXT": null,
    "AUTO_ETOR": null,
    "SPID": "3174141505",
    "fts_flag": "N",
    "geometry_x": -13608732.0522,
    "geometry_y": 4582730.5625
  },
  {
    "F_OUTAGE_ID": 2373037,
    "OUTAGE_EXTENT": "CUSTOMER",
    "OUTAGE_DEVICE_ID": "216879032110",
    "OUTAGE_CIRCUIT_ID": 42851121,
    "CREW_ETA": null,
    "CREW_CURRENT_STATUS": "Awaiting T-Man",
    "OUTAGE_CAUSE": "STORM",
    "EST_CUSTOMERS": 1,
    "OUTAGE_LATITUDE": 38.54337,
    "OUTAGE_LONGITUDE": -123.08802,
    "CITY": "Cazadero",
    "COUNTY": null,
    "ZIP": null,
    "DEVICE_COUNT": 0,
    "OUTAGE_START": 1707586440000,
    "OUTAGE_START_TEXT": null,
    "LAST_UPDATE": 1707622136000,
    "LAST_UPDATE_TEXT": null,
    "CURRENT_ETOR": null,
    "CURRENT_ETOR_TEXT": null,
    "AUTO_ETOR": null,
    "SPID": "3434108405",
    "fts_flag": "N",
    "geometry_x": -13702095.7092,
    "geometry_y": 4656472.716499999
  },
  {
    "F_OUTAGE_ID": 2373039,
    "OUTAGE_EXTENT": "CUSTOMER",
    "OUTAGE_DEVICE_ID": "315893117597",
    "OUTAGE_CIRCUIT_ID": 83692105,
    "CREW_ETA": null,
    "CREW_CURRENT_STATUS": "Awaiting T-Man",
    "OUTAGE_CAUSE": "STORM",
    "EST_CUSTOMERS": 1,
    "OUTAGE_LATITUDE": 36.97172,
    "OUTAGE_LONGITUDE": -121.90565,
    "CITY": "Seacliff",
    "COUNTY": null,
    "ZIP": null,
    "DEVICE_COUNT": 0,
    "OUTAGE_START": 1707600840000,
    "OUTAGE_START_TEXT": null,
    "LAST_UPDATE": 1707622466000,
    "LAST_UPDATE_TEXT": null,
    "CURRENT_ETOR": null,
    "CURRENT_ETOR_TEXT": null,
    "AUTO_ETOR": null,
    "SPID": "8903436105",
    "fts_flag": "N",
    "geometry_x": -13570474.8828,
    "geometry_y": 4435165.6526999995
  },
  {
    "F_OUTAGE_ID": 2373047,
    "OUTAGE_EXTENT": "CUSTOMER",
    "OUTAGE_DEVICE_ID": "317040021098",
    "OUTAGE_CIRCUIT_ID": 83182101,
    "CREW_ETA": null,
    "CREW_CURRENT_STATUS": "Awaiting T-Man",
    "OUTAGE_CAUSE": "STORM",
    "EST_CUSTOMERS": 1,
    "OUTAGE_LATITUDE": 37.07478,
    "OUTAGE_LONGITUDE": -121.51539,
    "CITY": "Gilroy",
    "COUNTY": null,
    "ZIP": null,
    "DEVICE_COUNT": 0,
    "OUTAGE_START": 1707603022000,
    "OUTAGE_START_TEXT": null,
    "LAST_UPDATE": 1707624628000,
    "LAST_UPDATE_TEXT": null,
    "CURRENT_ETOR": null,
    "CURRENT_ETOR_TEXT": null,
    "AUTO_ETOR": null,
    "SPID": "7901210705",
    "fts_flag": "N",
    "geometry_x": -13527031.3383,
    "geometry_y": 4449535.286899999
  },
  {
    "F_OUTAGE_ID": 2373048,
    "OUTAGE_EXTENT": "CUSTOMER",
    "OUTAGE_DEVICE_ID": "315300523286",
    "OUTAGE_CIRCUIT_ID": 82841101,
    "CREW_ETA": null,
    "CREW_CURRENT_STATUS": "Awaiting T-Man",
    "OUTAGE_CAUSE": "STORM",
    "EST_CUSTOMERS": 1,
    "OUTAGE_LATITUDE": 37.12876,
    "OUTAGE_LONGITUDE": -122.11097,
    "CITY": "Boulder Creek",
    "COUNTY": null,
    "ZIP": null,
    "DEVICE_COUNT": 0,
    "OUTAGE_START": 1707603600000,
    "OUTAGE_START_TEXT": null,
    "LAST_UPDATE": 1707625247000,
    "LAST_UPDATE_TEXT": null,
    "CURRENT_ETOR": null,
    "CURRENT_ETOR_TEXT": null,
    "AUTO_ETOR": null,
    "SPID": "8794095505",
    "fts_flag": "N",
    "geometry_x": -13593331.0007,
    "geometry_y": 4457069.499700002
  },
  {
    "F_OUTAGE_ID": 2373091,
    "OUTAGE_EXTENT": "CUSTOMER",
    "OUTAGE_DEVICE_ID": "315161551719",
    "OUTAGE_CIRCUIT_ID": 14671101,
    "CREW_ETA": null,
    "CREW_CURRENT_STATUS": "T-Man On Site",
    "OUTAGE_CAUSE": "PATROLLING",
    "EST_CUSTOMERS": 1,
    "OUTAGE_LATITUDE": 37.9085,
    "OUTAGE_LONGITUDE": -122.17795,
    "CITY": "Orinda",
    "COUNTY": null,
    "ZIP": null,
    "DEVICE_COUNT": 0,
    "OUTAGE_START": 1707620580000,
    "OUTAGE_START_TEXT": null,
    "LAST_UPDATE": 1707623822000,
    "LAST_UPDATE_TEXT": null,
    "CURRENT_ETOR": 1707645600000,
    "CURRENT_ETOR_TEXT": null,
    "AUTO_ETOR": 1707645600000,
    "SPID": "1628914005",
    "fts_flag": "N",
    "geometry_x": -13600787.1802,
    "geometry_y": 4566507.983199999
  },
  {
    "F_OUTAGE_ID": 2373092,
    "OUTAGE_EXTENT": "CUSTOMER",
    "OUTAGE_DEVICE_ID": "510773076555",
    "OUTAGE_CIRCUIT_ID": 183071104,
    "CREW_ETA": null,
    "CREW_CURRENT_STATUS": "T-Man Enroute",
    "OUTAGE_CAUSE": "STORM",
    "EST_CUSTOMERS": 1,
    "OUTAGE_LATITUDE": 35.56449,
    "OUTAGE_LONGITUDE": -121.10365,
    "CITY": "Cambria",
    "COUNTY": null,
    "ZIP": null,
    "DEVICE_COUNT": 0,
    "OUTAGE_START": 1707621660000,
    "OUTAGE_START_TEXT": null,
    "LAST_UPDATE": 1707623195000,
    "LAST_UPDATE_TEXT": null,
    "CURRENT_ETOR": null,
    "CURRENT_ETOR_TEXT": null,
    "AUTO_ETOR": null,
    "SPID": "397163105",
    "fts_flag": "N",
    "geometry_x": -13481196.6512,
    "geometry_y": 4240860.157499999
  }
]
